Workbook
Name NativeTimeline_Start_time: #N/A
Name NativeTimeline_Start_time1: #N/A

Sheet List of Employees
A1: Employee ID | B1: Old ID | C1: Employee Name | D1: Section | E1: Status | F1: Status Change Date | G1: Level | H1: Type | I1: Full Time Emplyee | J1: Remarks
A2: 12000013 | B2: EXP-011 | C2: Atta mohamed khalil | D2: Electrical | E2: Active | G2: Manager | H2: Expat | I2: Yes
A3: 12000022 | B3: EXP-038 | C3: Hassan Metwally | D3: Electrical | E3: Active | G3: Engineer | H3: Expat | I3: Yes
A4: 12000008 | B4: EXP-037 | C4: Hany Sheta | D4: Electrical | E4: Inactive | F4: 46204 | G4: Engineer | H4: Expat | I4: Yes
A5: 12000037 | B5: EXP-169 | C5: Ahmed Hamdy | D5: Electrical | E5: Inactive | F5: 45992 | G5: Engineer | H5: Expat | I5: Yes | J5: 45992
A6: 12000042 | B6: EXP-076 | C6: Ahmad Fajar | D6: Electrical | E6: Inactive | F6: 45962 | G6: Engineer | H6: Expat | I6: Yes | J6: 45962
A7: 12000041 | B7: EXP-088 | C7: Hazwal Ngadeni | D7: Electrical | E7: Active | G7: Engineer | H7: Expat | I7: Yes
A8: 12000040 | B8: EXP-128 | C8: Filipus Aron | D8: Electrical | E8: Inactive | F8: 45992 | G8: Engineer | H8: Expat | I8: Yes | J8: 45992
A9: 12000016 | B9: EXP-155 | C9: Rohit Bhogle | D9: Electrical | E9: Inactive | F9: 45992 | G9: Engineer | H9: Expat | I9: Yes | J9: 45992
A10: 12000043 | B10: EXP-133 | C10: Asnawi bin Kariman | D10: Electrical | E10: Inactive | F10: 46362 | G10: Supervisor | H10: Expat | I10: Yes
A11: 12000027 | B11: EXP-032 | C11: Osama Abdel Azeem | D11: Electrical | E11: Active | G11: Supervisor | H11: Expat | I11: Yes
A12: 12000032 | B12: EXP-034 | C12: Moustaf Abdel Naser | D12: Electrical | E12: Inactive | F12: 45992 | G12: Supervisor | H12: Expat | I12: Yes | J12: 45992
A13: 12000067 | B13: EXP-187 | C13: Salis Nader | D13: Electrical | E13: Inactive | F13: 45992 | G13: Supervisor | H13: Expat | I13: Yes | J13: 45992
A14: 12000071 | B14: EXP-078 | C14: Suryadi Sudari Arbain | D14: Electrical | E14: Inactive | F14: 45962 | G14: Supervisor | H14: Expat | I14: Yes | J14: 45962
A15: 12000064 | B15: EXP-077 | C15: Suherman Bin Masri | D15: Electrical | E15: Active | G15: Supervisor | H15: Expat | I15: Yes
A16: 12000026 | B16: BFI-224 | C16: Hajah Nur Izzyani Binti Haji Ramlee | D16: Electrical | E16: Active | G16: Engineer | H16: Bruneian | I16: Yes
A17: 12000031 | B17: BFI-223 | C17: Muhammed Abeed Bin Sarkawi | D17: Electrical | E17: Active | G17: Engineer | H17: Bruneian | I17: Yes
A18: 12000023 | B18: BFI-249 | C18: Naadhirah Mahmud | D18: Electrical | E18: Active | G18: Engineer | H18: Bruneian | I18: Yes
A19: 12000073 | B19: BFI-226 | C19: Muhammad Nur Faris Bin Haji Buhari | D19: Electrical | E19: Active | G19: Technician | H19: Bruneian | I19: Yes
A20: 12000034 | B20: BFI-242 | C20: Muhamad Aqhari bin Jamudin | D20: Electrical | E20: Active | G20: Technician | H20: Bruneian | I20: Yes
A21: 12000036 | B21: BFI-239 | C21: Mohammad Syukri Bin Safri | D21: Electrical | E21: Active | G21: Technician | H21: Bruneian | I21: Yes
A22: 12000066 | B22: BFI-234 | C22: Mohammad Hazieduddin bin Hussin | D22: Electrical | E22: Active | G22: Technician | H22: Bruneian | I22: Yes
A23: 12000072 | B23: BFI-236 | C23: Mohamed Husnir Rahman bin Osman | D23: Electrical | E23: Active | G23: Technician | H23: Bruneian | I23: Yes
A24: 12000035 | B24: BFI-241 | C24: Liyana Abd Rahim | D24: Electrical | E24: Active | G24: Technician | H24: Bruneian | I24: Yes
A25: 12000069 | B25: BFI-240 | C25: Saharin bin Rotan | D25: Electrical | E25: Active | G25: Technician | H25: Bruneian | I25: Yes
A26: 12000029 | B26: BFI-229 | C26: Ummi Farhanah bte Zulkifle | D26: Electrical | E26: Active | G26: Technician | H26: Bruneian | I26: Yes
... A34: 12000065 | B34: BFI-238 | C34: Md Faris Zullfikeri bin Hj Abd Rashid | D34: Electrical | E34: Active | G34: Technician | H34: Bruneian | I34: Yes
A35: 12000009 | C35: Ahmed Abdelrahman Mohammed Morsy | D35: Workshop | E35: Active | G35: Manager | H35: Expat | I35: Yes
A36: 12000142 | C36: Ahmed Reda Saleh Mohamed Khalifa | D36: Workshop | E36: Inactive | F36: 46023 | G36: Engineer | H36: Expat | I36: Yes | J36: 46023
A37: 12000011 | C37: Haji Suhaimi Bin Haji Julaihi | D37: Workshop | E37: Active | G37: Engineer | H37: Bruneian | I37: Yes
A38: 12000012 | C38: Emrullah Akman | D38: Workshop | E38: Inactive | F38: 46023 | G38: Engineer | H38: Expat | I38: Yes | J38: 46023
A39: 12000154 | C39: Mohammad Taufik Bin Hassan | D39: Workshop | E39: Active | G39: Engineer | H39: Expat | I39: Yes
A40: 12000068 | C40: Hamizah Mahmud | D40: Workshop | E40: Active | G40: Engineer | H40: Bruneian | I40: Yes
A41: 12000141 | C41: Suebsak Mahintarathep | D41: Workshop | E41: Active | G41: Supervisor | H41: Expat | I41: Yes
A42: 12000160 | C42: Masdirino Bin Suradi | D42: Workshop | E42: Active | G42: Technician | H42: Bruneian | I42: Yes
A43: 12000161 | C43: Asnie Bin Idris | D43: Workshop | E43: Active | G43: Technician | H43: Bruneian | I43: Yes
A44: 12000153 | C44: Muhammad Nikmatul Faris Bin Shamsul | D44: Workshop | E44: Active | G44: Technician | H44: Bruneian | I44: Yes
A45: 12000162 | C45: Junie Bin Idris | D45: Workshop | E45: Active | G45: Technician | H45: Bruneian | I45: Yes
A46: 12000166 | C46: Muhammad Nasrullah Joey Bin Abdullah Hong | D46: Workshop | E46: Active | G46: Technician | H46: Bruneian | I46: Yes
A47: 12000165 | C47: Sukhbir Singh | D47: Workshop | E47: Active | G47: Technician | H47: Expat | I47: Yes
A48: 12000155 | C48: Mohammad Abdul Khaliq Bin Alisan | D48: Workshop | E48: Active | G48: Technician | H48: Bruneian | I48: Yes
A49: 12000163 | C49: Mohammad Yusra Hakim Bin Hj Ramlee | D49: Workshop | E49: Active | G49: Technician | H49: Bruneian | I49: Yes
A50: 12000164 | C50: Muhammad Harriz Hazwan Bin Abdullah Tegong | D50: Workshop | E50: Active | G50: Technician | H50: Bruneian | I50: Yes
A51: 12000157 | C51: Rasel Rana | D51: Workshop | E51: Inactive | F51: 45992 | G51: Technician | H51: Expat | I51: Yes | J51: 45992
A52: 12000158 | C52: Mohd Salihin Abdullah | D52: Workshop | E52: Inactive | F52: 45992 | G52: Technician | H52: Expat | I52: Yes | J52: 45992
A53: 12000015 | C53: Sumbang Anak Rentap | D53: Workshop | E53: Inactive | F53: 45992 | G53: Technician | H53: Expat | I53: Yes | J53: 45992
A54: 12000017 | C54: Muhammad Ridhwan Bin Haji Rahman | D54: Workshop | E54: Active | G54: Technician | H54: Bruneian | I54: Yes
A55: 12000080 | C55: Le Toan Linh | D55: Workshop | E55: Active | G55: Technician | H55: Expat | I55: Yes
A56: 12000079 | C56: Mohammad Faiz Ahmad | D56: Workshop | E56: Inactive | F56: 45992 | G56: Technician | H56: Expat | I56: Yes | J56: 45992
A57: 12000148 | C57: Muhammad Ali Shafie Bin Haji Ali Sabahrin | D57: Workshop | E57: Active | G57: Technician | H57: Bruneian | I57: Yes
A58: 12000144 | C58: Madhukar Prasad Gupta | D58: Workshop | E58: Inactive | F58: 45992 | G58: Technician | H58: Expat | I58: Yes | J58: 45992
A59: 12000076 | C59: Mohammad Shamim Afzal | D59: Workshop | E59: Inactive | F59: 45992 | G59: Technician | H59: Expat | I59: Yes | J59: 45992
A60: 12000078 | C60: Naushad Ahmad Siddique | D60: Workshop | E60: Inactive | F60: 45992 | G60: Technician | H60: Expat | I60: Yes | J60: 45992
A61: 12000147 | C61: Nurzahirulhaq Mostar Bin Shafiee | D61: Workshop | E61: Active | G61: Technician | H61: Bruneian | I61: Yes
A62: 12000075 | C62: Mohamed Aizzudin Bin Awang Haji Tuah | D62: Workshop | E62: Active | G62: Technician | H62: Bruneian | I62: Yes
A63: 12000156 | C63: Jaosoa Francklin | D63: Workshop | E63: Active | G63: Technician | H63: Expat | I63: Yes
A64: 12000151 | C64: Abdul Haziq Bin Abdul Hamid | D64: Workshop | E64: Active | G64: Technician | H64: Bruneian | I64: Yes
A65: 12000145 | C65: Romel Samillano Rubido | D65: Workshop | E65: Active | G65: Technician | H65: Expat | I65: Yes
A66: 12000149 | C66: Yusde Bin Junaidi | D66: Workshop | E66: Active | G66: Technician | H66: Bruneian | I66: Yes
A67: iR-052 | C67: Martin bin Juin | D67: Workshop | E67: Inactive | F67: 45992 | H67: Bruneian | I67: No | J67: Iready
A68: 12000227 | C68: Mohammad Afiq bin Awang | D68: Workshop | E68: Active | G68: Engineer | H68: Bruneian | I68: Yes
A69: 12000061 | C69: Mohamed Moussa | D69: Static | E69: Inactive | F69: 45992 | G69: Engineer | H69: Expat | I69: Yes | J69: December 2025
A70: 12000062 | C70: Naveed Bashir | D70: Static | E70: Inactive | G70: Engineer | H70: Expat | I70: Yes
A71: 12000054 | C71: Muhammad Ismail | D71: Static | E71: Inactive | F71: 45992 | G71: Technician | H71: Expat | I71: Yes | J71: December 2025
A72: 12000055 | C72: Ahmad Ikhsan | D72: Static | E72: Inactive | F72: 45992 | G72: Technician | H72: Expat | I72: Yes | J72: December 2025
A73: 12000115 | C73: M. Fazill Bin Awang Hj Sulaiman | D73: Static | E73: Active | G73: Technician | H73: Bruneian | I73: Yes
A74: 12000105 | C74: M. Zulhelmi Bin Hj Asmawi | D74: Static | E74: Active | G74: Technician | H74: Bruneian | I74: Yes
A75: 12000117 | C75: Mohamed Othman | D75: Static | E75: Active | G75: Engineer | H75: Expat | I75: Yes
A76: 12000057 | C76: Nauman Anjum | D76: Static | E76: Inactive | F76: 45992 | G76: Engineer | H76: Expat | I76: Yes | J76: December 2025
A77: 12000108 | C77: Low Choon Ping | D77: Static | E77: Active | G77: Engineer | H77: Bruneian | I77: Yes
A78: 12000058 | C78: Abdul Wahid | D78: Static | E78: Active | G78: Supervisor | H78: Expat | I78: Yes
A79: 12000136 | C79: Mahendra S. Patel | D79: Static | E79: Active | G79: Technician | H79: Expat | I79: Yes
A80: 12000059 | C80: Shiju Varghese | D80: Static | E80: Active | G80: Technician | H80: Expat | I80: Yes
A81: 12000114 | C81: Muhammad Hakim bin Abdullah | D81: Static | E81: Active | G81: Technician | H81: Bruneian | I81: Yes
A82: 12000112 | C82: Abdul Khaliq Haji Adinin | D82: Static | E82: Active | G82: Technician | H82: Bruneian | I82: Yes
A83: 12000051 | C83: Tamer Ahmed | D83: Static | E83: Inactive | G83: Engineer | H83: Expat | I83: Yes
A84: 12000109 | C84: Ti Zhi Yuan | D84: Static | E84: Active | G84: Engineer | H84: Bruneian | I84: Yes
A85: 12000053 | C85: Ayman sayed Abdelrehim Radwan | D85: Static | E85: Inactive | F85: 45992 | G85: Supervisor | H85: Expat | I85: Yes | J85: December 2025
A86: 12000056 | C86: Ram Pratap Nishad | D86: Static | E86: Active | G86: Technician | H86: Expat | I86: Yes
A87: 12000060 | C87: Sharifkhan Amanullakhan Pathan | D87: Static | E87: Active | G87: Technician | H87: Expat | I87: Yes
A88: 12000102 | C88: Muhammad Akmal Muntaqim bin Haji Bakeri | D88: Static | E88: Active | G88: Technician | H88: Bruneian | I88: Yes
A89: 12000104 | C89: Yusof young | D89: Static | E89: Active | G89: Technician | H89: Bruneian | I89: Yes
A90: 12000014 | C90: Mohamed Yousef Shebl Aly Nassar | D90: Instrument | E90: Active | G90: Manager | H90: Expat | I90: Yes
A91: 12000077 | C91: Galant Putra | D91: Instrument | E91: Active | G91: Engineer | H91: Expat | I91: Yes
A92: 12000082 | C92: Mahmoud Fakhry Ahmed Elnemr | D92: Instrument | E92: Active | G92: Engineer | H92: Expat | I92: Yes
A93: 12000084 | C93: Nurasilah binti Hj Ismail | D93: Instrument | E93: Active | G93: Engineer | H93: Bruneian | I93: Yes
A94: 12000087 | B94: BFI255 | C94: Mohd Amin Tamrin bin Hj Mohd Talip | D94: Instrument | E94: Active | G94: Technician | H94: Bruneian | I94: Yes
A95: 12000088 | B95: BFI263 | C95: Muhd Hishamuddin bin Edis Asmena | D95: Instrument | E95: Active | G95: Technician | H95: Bruneian | I95: Yes
A96: 12000090 | B96: 12000090 | C96: Nur Izyan Yakup | D96: Instrument | E96: Active | G96: Technician | H96: Bruneian | I96: Yes
A97: 12000092 | C97: Hamza Masood Raja | D97: Instrument | E97: Inactive | G97: Engineer | H97: Expat | I97: Yes
A98: 12000093 | C98: Mohd 'Arif bin Sahari | D98: Instrument | E98: Active | G98: Engineer | H98: Bruneian | I98: Yes
A99: 12000094 | C99: Nur Aqilah binti Hj Abdullah | D99: Instrument | E99: Active | G99: Engineer | H99: Bruneian | I99: Yes
A100: 12000096 | C100: Yehya Gooda Mohamed Mostafa | D100: Instrument | E100: Inactive | G100: Supervisor | H100: Expat | I100: Yes
A101: 12000099 | B101: BFI252 | C101: Abdul Badri Izdihar Bin Hj Abd Lamit | D101: Instrument | E101: Active | G101: Technician | H101: Bruneian | I101: Yes
A102: 12000103 | B102: BFI259 | C102: Marahaini Rafidah Binti Abdullah | D102: Instrument | E102: Active | G102: Technician | H102: Bruneian | I102: Yes
A103: 12000106 | C103: Rhea Nurramizah binti Abdullah Bajing | D103: Instrument | E103: Active | G103: Engineer | H103: Bruneian | I103: Yes
A104: 12000107 | C104: Mohamed Abdelrahman Mohamed Goumaa | D104: Instrument | E104: Active | G104: Supervisor | H104: Expat | I104: Yes
A105: 12000110 | B105: BFI260 | C105: Nur Atiqah Aziqah binti Zaini | D105: Instrument | E105: Active | G105: Technician | H105: Bruneian | I105: Yes
A106: 12000111 | B106: BFI244 | C106: Nur Zawani Binti Marrot | D106: Instrument | E106: Active | G106: Technician | H106: Bruneian | I106: Yes
A107: 12000113 | B107: BFI258 | C107: Muhd Azaim Bin Hj Mohd Jamali | D107: Instrument | E107: Active | G107: Technician | H107: Bruneian | I107: Yes
...

Sheet Care Card Per Employee
A1: Company / Organisation | B1: (BRE) Brunei Rotary Engineering
A2: Employee Status | B2: (Multiple Items) | C2: Max. till the Month | D2: 6
A3: Status | B3: (Multiple Items)
C4: Rectified Number
A5: Row Labels | B5: No of CARE Cards | C5: =IF(B5>$D$2,$D$2,B5) -> 6
A6: Muhammad Ali Shafie Bin Haji Ali Sabahrin | B6: 66 | C6: =IF(B6>$D$2,$D$2,B6) -> 6
A7: Ram Pratap Nishad | B7: 22 | C7: =IF(B7>$D$2,$D$2,B7) -> 6
A8: Yusof young | B8: 20 | C8: =IF(B8>$D$2,$D$2,B8) -> 6
A9: Muhammad Akmal Muntaqim bin Haji Bakeri | B9: 19 | C9: =IF(B9>$D$2,$D$2,B9) -> 6
A10: Shahminan Chamsuddin | B10: 18 | C10: =IF(B10>$D$2,$D$2,B10) -> 6
A11: Muhammad Hakim bin Abdullah | B11: 18 | C11: =IF(B11>$D$2,$D$2,B11) -> 6
A12: Mohammad Hazieduddin bin Hussin | B12: 17 | C12: =IF(B12>$D$2,$D$2,B12) -> 6
A13: Mohamed Khalil Ashalla Bagdad | B13: 16 | C13: =IF(B13>$D$2,$D$2,B13) -> 6
A14: Suebsak Mahintarathep | B14: 16 | C14: =IF(B14>$D$2,$D$2,B14) -> 6
A15: Mohd Afiq Taufiq bin Hj Mohd Talip | B15: 16 | C15: =IF(B15>$D$2,$D$2,B15) -> 6
A16: Mohd 'Arif bin Sahari | B16: 16 | C16: =IF(B16>$D$2,$D$2,B16) -> 6
A17: Muhammad Firdaus bin Muhammad Amry | B17: 15 | C17: =IF(B17>$D$2,$D$2,B17) -> 6
... A121: Grand Total | B121: 1122 | C121: =IF(B121>$D$2,$D$2,B121) -> 6
C122: =IF(B122>$D$2,$D$2,B122) -> 0
C123: =IF(B123>$D$2,$D$2,B123) -> 0
C124: =IF(B124>$D$2,$D$2,B124) -> 0

Sheet YTD Records
A1: Name | B1: YTD Number | C1: Status | D1: Employee ID
A2: ='Care Card Per Employee'!A6 -> Muhammad Ali Shafie Bin Haji Ali Sabahrin | B2: ='Care Card Per Employee'!C6 -> 6 | C2: {=_xlfn.XLOOKUP(Table7[[#This Row],[Name]],Table1[[#All],[Employee Name]],Table1[[#All],[Status]],"",0,1)} -> Active | D2: {=_xlfn.XLOOKUP(Table7[[#This Row],[Name]],Table1[[#All],[Employee Name]],Table1[[#All],[Employee ID]],"",0,1)} -> 12000148
A3: ='Care Card Per Employee'!A7 -> Ram Pratap Nishad | B3: ='Care Card Per Employee'!C7 -> 6 | C3: {=_xlfn.XLOOKUP(Table7[[#This Row],[Name]],Table1[[#All],[Employee Name]],Table1[[#All],[Status]],"",0,1)} -> Active | D3: {=_xlfn.XLOOKUP(Table7[[#This Row],[Name]],Table1[[#All],[Employee Name]],Table1[[#All],[Employee ID]],"",0,1)} -> 12000056
A4: ='Care Card Per Employee'!A8 -> Yusof young | B4: ='Care Card Per Employee'!C8 -> 6 | C4: {=_xlfn.XLOOKUP(Table7[[#This Row],[Name]],Table1[[#All],[Employee Name]],Table1[[#All],[Status]],"",0,1)} -> Active | D4: {=_xlfn.XLOOKUP(Table7[[#This Row],[Name]],Table1[[#All],[Employee Name]],Table1[[#All],[Employee ID]],"",0,1)} -> 12000104
A5: ='Care Card Per Employee'!A9 -> Muhammad Akmal Muntaqim bin Haji Bakeri | B5: ='Care Card Per Employee'!C9 -> 6 | C5: {=_xlfn.XLOOKUP(Table7[[#This Row],[Name]],Table1[[#All],[Employee Name]],Table1[[#All],[Status]],"",0,1)} -> Active | D5: {=_xlfn.XLOOKUP(Table7[[#This Row],[Name]],Table1[[#All],[Employee Name]],Table1[[#All],[Employee ID]],"",0,1)} -> 12000102
A6: ='Care Card Per Employee'!A10 -> Shahminan Chamsuddin | B6: ='Care Card Per Employee'!C10 -> 6 | C6: {=_xlfn.XLOOKUP(Table7[[#This Row],[Name]],Table1[[#All],[Employee Name]],Table1[[#All],[Status]],"",0,1)} -> Active | D6: {=_xlfn.XLOOKUP(Table7[[#This Row],[Name]],Table1[[#All],[Employee Name]],Table1[[#All],[Employee ID]],"",0,1)} -> 12000134
A7: ='Care Card Per Employee'!A11 -> Muhammad Hakim bin Abdullah | B7: ='Care Card Per Employee'!C11 -> 6 | C7: {=_xlfn.XLOOKUP(Table7[[#This Row],[Name]],Table1[[#All],[Employee Name]],Table1[[#All],[Status]],"",0,1)} -> Active | D7: {=_xlfn.XLOOKUP(Table7[[#This Row],[Name]],Table1[[#All],[Employee Name]],Table1[[#All],[Employee ID]],"",0,1)} -> 12000114
A8: ='Care Card Per Employee'!A12 -> Mohammad Hazieduddin bin Hussin | B8: ='Care Card Per Employee'!C12 -> 6 | C8: {=_xlfn.XLOOKUP(Table7[[#This Row],[Name]],Table1[[#All],[Employee Name]],Table1[[#All],[Status]],"",0,1)} -> Active | D8: {=_xlfn.XLOOKUP(Table7[[#This Row],[Name]],Table1[[#All],[Employee Name]],Table1[[#All],[Employee ID]],"",0,1)} -> 12000066
A9: ='Care Card Per Employee'!A13 -> Mohamed Khalil Ashalla Bagdad | B9: ='Care Card Per Employee'!C13 -> 6 | C9: {=_xlfn.XLOOKUP(Table7[[#This Row],[Name]],Table1[[#All],[Employee Name]],Table1[[#All],[Status]],"",0,1)} -> Active | D9: {=_xlfn.XLOOKUP(Table7[[#This Row],[Name]],Table1[[#All],[Employee Name]],Table1[[#All],[Employee ID]],"",0,1)} -> 12000010
A10: ='Care Card Per Employee'!A14 -> Suebsak Mahintarathep | B10: ='Care Card Per Employee'!C14 -> 6 | C10: {=_xlfn.XLOOKUP(Table7[[#This Row],[Name]],Table1[[#All],[Employee Name]],Table1[[#All],[Status]],"",0,1)} -> Active | D10: {=_xlfn.XLOOKUP(Table7[[#This Row],[Name]],Table1[[#All],[Employee Name]],Table1[[#All],[Employee ID]],"",0,1)} -> 12000141
A11: ='Care Card Per Employee'!A15 -> Mohd Afiq Taufiq bin Hj Mohd Talip | B11: ='Care Card Per Employee'!C15 -> 6 | C11: {=_xlfn.XLOOKUP(Table7[[#This Row],[Name]],Table1[[#All],[Employee Name]],Table1[[#All],[Status]],"",0,1)} -> Active | D11: {=_xlfn.XLOOKUP(Table7[[#This Row],[Name]],Table1[[#All],[Employee Name]],Table1[[#All],[Employee ID]],"",0,1)} -> 12000126
A12: ='Care Card Per Employee'!A16 -> Mohd 'Arif bin Sahari | B12: ='Care Card Per Employee'!C16 -> 6 | C12: {=_xlfn.XLOOKUP(Table7[[#This Row],[Name]],Table1[[#All],[Employee Name]],Table1[[#All],[Status]],"",0,1)} -> Active | D12: {=_xlfn.XLOOKUP(Table7[[#This Row],[Name]],Table1[[#All],[Employee Name]],Table1[[#All],[Employee ID]],"",0,1)} -> 12000093
A13: ='Care Card Per Employee'!A17 -> Muhammad Firdaus bin Muhammad Amry | B13: ='Care Card Per Employee'!C17 -> 6 | C13: {=_xlfn.XLOOKUP(Table7[[#This Row],[Name]],Table1[[#All],[Employee Name]],Table1[[#All],[Status]],"",0,1)} -> Active | D13: {=_xlfn.XLOOKUP(Table7[[#This Row],[Name]],Table1[[#All],[Employee Name]],Table1[[#All],[Employee ID]],"",0,1)} -> 12000202
... A116: ='Care Card Per Employee'!A120 -> Mahindra patil | B116: ='Care Card Per Employee'!C120 -> 1 | C116: {=_xlfn.XLOOKUP(Table7[[#This Row],[Name]],Table1[[#All],[Employee Name]],Table1[[#All],[Status]],"",0,1)} -> Active | D116: {=_xlfn.XLOOKUP(Table7[[#This Row],[Name]],Table1[[#All],[Employee Name]],Table1[[#All],[Employee ID]],"",0,1)} -> 12000136

Sheet HSSE Records
A1: Id | B1: Start time | C1: Completion time | D1: Email | E1: Date of Intervention / Tarikh ketika Membuat Teguran Care Card | F1: Full Name / Nama Penuh | G1: BFI Number (BFI000 / EXP000) | H1: Company / Organisation | I1: Position | J1: Location of Interventions / Lokasi tempat kamu buat teguran | K1: Purpose of Care Card Interventions / Tujuan Teguran Care Card Anda | L1: What have you Observed, Seen or Encountered? / Apa yang kamu nampak, alami atau perhatikan? | M1: What can go wrong if there's no interventions or actions has been made? / Apa boleh terjadi sekiranya tiada tindakan dilakukan? | N1: What have you done to solve the problem(s)? How did you approach the person to make interventions? / How do you support the Good Practice? What do you suggest for the Item you highlighted? / Apakah ti | O1: Category of this Care Card Submission / Kategori Teguran Care Card Anda | P1: Status | Q1: Employee Status | R1: Near Miss
A2: 7376 | B2: 46203.683 | C2: 46203.688 | D2: anonymous | E2: 46203 | F2: Mohamed Khalil Ashalla Bagdad | G2: 12000010 | H2: (BRE) Brunei Rotary Engineering | I2: RE &SE Section Manager | J2: Ammonia Plant | K2: Unsafe Condition (Dangerous Area that has potential to cause harm or injury to People within the Area) / Keadaan Bahaya | L2: A horizontal beam has been observed across the flue gas blower ladder access. head injury for personnel climbing the ladder can be occurred Re locating the beam and Painting it with a different and noticeable colour are required | M2: Injures might be happened | N2: Informing project team | O2: Design and Engineering / Tempat Pekerjaan kurang sesuai | P2: Done | Q2: {=_xlfn.XLOOKUP(Table4[[#This Row],[Full Name / Nama Penuh]],Table1[[#All],[Employee Name]],Table1[[#All],[Status]],"",0,1)} -> Active
A3: 7381 | B3: 46203.795 | C3: 46203.802 | D3: anonymous | E3: 46203 | F3: Mohammad Noorhamdillah bin Zakaria | G3: 12000081 | H3: (BRE) Brunei Rotary Engineering | I3: Mechanical rotating engineer | J3: Offsite & Utilities | K3: Unsafe Condition (Dangerous Area that has potential to cause harm or injury to People within the Area) / Keadaan Bahaya | L3: Open drain at chemical dosing skid | M3: Trip and fall hazard | N3: Suggestion to install drain cover | O3: Design and Engineering / Tempat Pekerjaan kurang sesuai | P3: Done | Q3: {=_xlfn.XLOOKUP(Table4[[#This Row],[Full Name / Nama Penuh]],Table1[[#All],[Employee Name]],Table1[[#All],[Status]],"",0,1)} -> Active
A4: 7366 | B4: 46203.487 | C4: 46203.49 | D4: anonymous | E4: 46203 | F4: Mohd Syahmi Bin Jamalluddin | G4: 12000137 | H4: (BRE) Brunei Rotary Engineering | I4: Instrument Technician | J4: North Building First Floor | K4: Unsafe Condition (Dangerous Area that has potential to cause harm or injury to People within the Area) / Keadaan Bahaya | L4: No adhesive grip tapes present on the floor of the stairs | M4: Personnel may slip and trip and they may injure themselves | N4: Informed the team that can address this issue | O4: Hazardous - Unsafe Environment / Situasi Tempat Kerja yang Berbahaya untuk Alam Sekitar | P4: Done | Q4: {=_xlfn.XLOOKUP(Table4[[#This Row],[Full Name / Nama Penuh]],Table1[[#All],[Employee Name]],Table1[[#All],[Status]],"",0,1)} -> Active
A5: 7382 | B5: 46203.802 | C5: 46203.814 | D5: anonymous | E5: 46203 | F5: Mohammad Noorhamdillah bin Zakaria | G5: 12000081 | H5: (BRE) Brunei Rotary Engineering | I5: Maintenance mechanical engineer | J5: Offsite & Utilities | K5: Safe Act or Positive Practice (An appreciation to be made to that person who shows good examples) / Kelakuan yang Baik | L5: Good housekeeping maintained at work area | M5: - | N5: Raise care card to encourage and appreciate the positive act | O5: Proactive Approach / Teguran Positif (Safe Act / Positive Act) | P5: Done | Q5: {=_xlfn.XLOOKUP(Table4[[#This Row],[Full Name / Nama Penuh]],Table1[[#All],[Employee Name]],Table1[[#All],[Status]],"",0,1)} -> Active
A6: 7377 | B6: 46203.698 | C6: 46203.704 | D6: anonymous | E6: 46203 | F6: Mohamed Othman | G6: 12000117 | H6: (BRE) Brunei Rotary Engineering | I6: Mechanical lead | J6: Urea Plant | K6: Safe Act or Positive Practice (An appreciation to be made to that person who shows good examples) / Kelakuan yang Baik | L6: Securing all granulation doors so no humidity or birds enter | M6: Birds and accumulated humidity | N6: Confirming open doors are closed | O6: Individual Behaviour / Tingkah Laku yang Cuai dan Berbahaya | P6: Done | Q6: {=_xlfn.XLOOKUP(Table4[[#This Row],[Full Name / Nama Penuh]],Table1[[#All],[Employee Name]],Table1[[#All],[Status]],"",0,1)} -> Active
A7: 7374 | B7: 46203.649 | C7: 46203.652 | D7: anonymous | E7: 46203 | F7: Liyana Abd Rahim | G7: 12000035 | H7: (BRE) Brunei Rotary Engineering | I7: Technician | J7: Offsite & Utilities | K7: Improvement Suggestions / Cadangan untuk diperbaiki | L7: Someone falling down from bicycle because of blue cable | M7: More people will fall down | N7: Give suggestion | O7: Design and Engineering / Tempat Pekerjaan kurang sesuai | P7: Done | Q7: {=_xlfn.XLOOKUP(Table4[[#This Row],[Full Name / Nama Penuh]],Table1[[#All],[Employee Name]],Table1[[#All],[Status]],"",0,1)} -> Active
A8: 7365 | B8: 46203.477 | C8: 46203.487 | D8: anonymous | E8: 46203 | F8: Mohd Syahmi Bin Jamalluddin | G8: 12000137 | H8: (BRE) Brunei Rotary Engineering | I8: Instrument Technician | J8: Site Office First Floor | K8: Improvement Suggestions / Cadangan untuk diperbaiki | L8: No adhesive grip tapes on the stairs | M8: People may slip and injure themselves | N8: Raise this concern to the respective party to address this issue | O8: Hazardous - Unsafe Environment / Situasi Tempat Kerja yang Berbahaya untuk Alam Sekitar | P8: Done | Q8: {=_xlfn.XLOOKUP(Table4[[#This Row],[Full Name / Nama Penuh]],Table1[[#All],[Employee Name]],Table1[[#All],[Status]],"",0,1)} -> Active
A9: 7354 | B9: 46203.333 | C9: 46203.347 | D9: anonymous | E9: 46202 | F9: Naadhirah Mahmud | G9: 12000023 | H9: (BRE) Brunei Rotary Engineering | I9: Electrical Engineer | J9: Offsite & Utilities | K9: Unsafe Act (Dangerous or Unsafe Act that was done by someone) / Perbuatan Bahaya | L9: i saw someone texting while walking. | M9: she could fall because she was not paying attention. | N9: informed the person to step aside and reply to texts rather than texting while walking. | O9: Individual Behaviour / Tingkah Laku yang Cuai dan Berbahaya | P9: Done | Q9: {=_xlfn.XLOOKUP(Table4[[#This Row],[Full Name / Nama Penuh]],Table1[[#All],[Employee Name]],Table1[[#All],[Status]],"",0,1)} -> Active
A10: 7313 | B10: 46202.58 | C10: 46202.584 | D10: anonymous | E10: 46202 | F10: Shamiza binti Hussin | G10: 12000025 | H10: (BRE) Brunei Rotary Engineering | I10: Electrical Technician | J10: Site Office First Floor | K10: Unsafe Act (Dangerous or Unsafe Act that was done by someone) / Perbuatan Bahaya | L10: a personel was seen going upstair with his shoelace undone | M10: he may slip, trip and fall | N10: stop him and ask him to tie his shoelace | O10: Individual Behaviour / Tingkah Laku yang Cuai dan Berbahaya | P10: Done | Q10: {=_xlfn.XLOOKUP(Table4[[#This Row],[Full Name / Nama Penuh]],Table1[[#All],[Employee Name]],Table1[[#All],[Status]],"",0,1)} -> Active
A11: 7339 | B11: 46203.257 | C11: 46203.259 | D11: anonymous | E11: 46202 | F11: Mohammad Nabil Haji Gapor | G11: 12000044 | H11: (BRE) Brunei Rotary Engineering | I11: Lead Electrical Technician | J11: Trailer Parking Area | K11: Unsafe Condition (Dangerous Area that has potential to cause harm or injury to People within the Area) / Keadaan Bahaya | L11: almost got bitten by the dogs | M11: someone get bitten | N11: catch the dog and put them somewhere safer and better | O11: Hazardous - Unsafe Materials / Benda yang Berbahaya | P11: Done | Q11: {=_xlfn.XLOOKUP(Table4[[#This Row],[Full Name / Nama Penuh]],Table1[[#All],[Employee Name]],Table1[[#All],[Status]],"",0,1)} -> Active
A12: 7307 | B12: 46202.511 | C12: 46202.513 | D12: anonymous | E12: 46202 | F12: Vinod Kumar Verma | G12: 12000050 | H12: (BRE) Brunei Rotary Engineering | I12: Rotating technician | J12: North Building Ground Floor | K12: Unsafe Condition (Dangerous Area that has potential to cause harm or injury to People within the Area) / Keadaan Bahaya | L12: drainage water came out | M12: smell slip trip fall | N12: please inform to vaccum truck and clean this pit | O12: Hazardous - Unsafe Materials / Benda yang Berbahaya | P12: Done | Q12: {=_xlfn.XLOOKUP(Table4[[#This Row],[Full Name / Nama Penuh]],Table1[[#All],[Employee Name]],Table1[[#All],[Status]],"",0,1)} -> Active
A13: 7315 | B13: 46202.715 | C13: 46202.72 | D13: anonymous | E13: 46202 | F13: Ti Zhi Yuan | G13: 12000109 | H13: (BRE) Brunei Rotary Engineering | I13: Static Engineer | J13: Car Park near North Building | K13: Unsafe Act (Dangerous or Unsafe Act that was done by someone) / Perbuatan Bahaya | L13: Driving fast at car park area | M13: Accident causing minor/serious injury to passerby | N13: Intervene the driver to follow the speed limit | O13: Individual Behaviour / Tingkah Laku yang Cuai dan Berbahaya | P13: Done | Q13: {=_xlfn.XLOOKUP(Table4[[#This Row],[Full Name / Nama Penuh]],Table1[[#All],[Employee Name]],Table1[[#All],[Status]],"",0,1)} -> Active
... A165: 7061 | B165: 46181.433 | C165: 46181.438 | D165: anonymous | E165: 46181 | F165: Masdirino Bin Suradi | G165: 12000160 | H165: (BRE) Brunei Rotary Engineering | I165: HVAC TECHNICIAN | J165: Workshop | K165: Unsafe Condition (Dangerous Area that has potential to cause harm or injury to People within the Area) / Keadaan Bahaya | L165: Discovered that the safety interlocking guard on the fabrication workshop milling machine was bypassed with tape, allowing the machine to operate while the protective shield was wide open. | M165: Operators could easily make accidental contact with high-speed rotating parts, leading to severe lacerations, entanglement, or traumatic amputation of limbs. | N165: Enforced immediate machine shutdown and applied a Lockout/Tagout (LOTO) tag. Confronted the operator regarding the life-saving rule violation and raised the issue to the Workshop Supervisor. | O165: Tools, Equipment and Machinery / Berkaitan dengan Alat Kegunaan Pekerjaan dan Mesin sama ada ianya Tidak Sesuai untuk aktivitas tersebut atau sebaliknya | P165: Done | Q165: {=_xlfn.XLOOKUP(Table4[[#This Row],[Full Name / Nama Penuh]],Table1[[#All],[Employee Name]],Table1[[#All],[Status]],"",0,1)} -> Active
A166: 5889 | B166: 46120.552 | C166: 46120.554 | D166: anonymous | E166: 46181 | F166: Yusof young | H166: (BRE) Brunei Rotary Engineering | I166: static | J166: Ammonia Plant | K166: Safe Act or Positive Practice (An appreciation to be made to that person who shows good examples) / Kelakuan yang Baik | L166: co worker following the required safety regulation from the permit to work suggested by the pip | M166: N/A | N166: tell him to keep it up | O166: Proactive Approach / Teguran Positif (Safe Act / Positive Act) | P166: Done | Q166: {=_xlfn.XLOOKUP(Table4[[#This Row],[Full Name / Nama Penuh]],Table1[[#All],[Employee Name]],Table1[[#All],[Status]],"",0,1)} -> Active
A167: 7196 | B167: 46195.629 | C167: 46195.629 | D167: anonymous | E167: 46181 | F167: Ram Pratap Nishad | G167: 12000056 | H167: (BRE) Brunei Rotary Engineering | I167: Senior Static Technician | J167: Ammonia Plant | K167: Safe Act or Positive Practice (An appreciation to be made to that person who shows good examples) / Kelakuan yang Baik | L167: 1071P002A, pump suction strainer cleaning work | M167: Safe working behaviour found | N167: Safe work | O167: Individual Behaviour / Tingkah Laku yang Cuai dan Berbahaya | P167: Done | Q167: {=_xlfn.XLOOKUP(Table4[[#This Row],[Full Name / Nama Penuh]],Table1[[#All],[Employee Name]],Table1[[#All],[Status]],"",0,1)} -> Active
A168: 7100 | B168: 46184.484 | C168: 46184.487 | D168: anonymous | E168: 46181 | F168: Abdul Khaliq Haji Adinin | G168: 12000112 | H168: (BRE) Brunei Rotary Engineering | I168: Static Technician | J168: Main Gate 1 | K168: Safe Act or Positive Practice (An appreciation to be made to that person who shows good examples) / Kelakuan yang Baik | L168: Saw security personal intervene one contractor personal where he’s about to go inside the site with rolled up sleeves, where it does not met proper attire etiquette | M168: Not using proper PPE is a violation and also can cause harm whenever he’s inside the plant since there’s a lot of hazard around the area | N168: Praise the security personal as he intervene in good and safe manner to the personal | O168: Proactive Approach / Teguran Positif (Safe Act / Positive Act) | P168: Done | Q168: {=_xlfn.XLOOKUP(Table4[[#This Row],[Full Name / Nama Penuh]],Table1[[#All],[Employee Name]],Table1[[#All],[Status]],"",0,1)} -> Active
A169: 7072 | B169: 46181.539 | C169: 46181.543 | D169: anonymous | E169: 46181 | F169: Dk NoorFaszalenna Pg Zaini | G169: 12000024 | H169: (BRE) Brunei Rotary Engineering | I169: Electrical Technician | J169: Electrical Substation | K169: Safe Act or Positive Practice (An appreciation to be made to that person who shows good examples) / Kelakuan yang Baik | L169: Saw a personnel stopping another person who is working on electrical equipment to use handgloves | M169: - | N169: - | O169: Proactive Approach / Teguran Positif (Safe Act / Positive Act) | P169: Done | Q169: {=_xlfn.XLOOKUP(Table4[[#This Row],[Full Name / Nama Penuh]],Table1[[#All],[Employee Name]],Table1[[#All],[Status]],"",0,1)} -> Active
A170: 7070 | B170: 46181.522 | C170: 46181.53 | D170: anonymous | E170: 46181 | F170: Jaosoa Francklin | G170: 12000156 | H170: (BRE) Brunei Rotary Engineering | I170: Valve Technician | J170: Workshop | K170: Improvement Suggestions / Cadangan untuk diperbaiki | L170: Currently we notice more and more bird comes and dwelled inside MSL workshop. Though we have sensitive Equipment inside. And our devices are likely covered by bird excrements. | M170: Fore sure we clean but this can affect life time and efficiency if reached critical parts | N170: we are trying to keep equipment as clean as possible and covered them after shift but it become complicate since more bird live inside. | O170: Facility Management / Perawatan Kemudahan dan Aset | P170: Done | Q170: {=_xlfn.XLOOKUP(Table4[[#This Row],[Full Name / Nama Penuh]],Table1[[#All],[Employee Name]],Table1[[#All],[Status]],"",0,1)} -> Active
A171: 5889 | B171: 46120.552 | C171: 46120.554 | D171: anonymous | E171: 46181 | F171: Yusof young | G171: 12000104 | H171: (BRE) Brunei Rotary Engineering | I171: static | J171: Ammonia Plant | K171: Safe Act or Positive Practice (An appreciation to be made to that person who shows good examples) / Kelakuan yang Baik | L171: co worker following the required safety regulation from the permit to work suggested by the pip | M171: N/A | N171: tell him to keep it up | O171: Proactive Approach / Teguran Positif (Safe Act / Positive Act) | P171: Done | Q171: {=_xlfn.XLOOKUP(Table4[[#This Row],[Full Name / Nama Penuh]],Table1[[#All],[Employee Name]],Table1[[#All],[Status]],"",0,1)} -> Active
A172: 7056 | B172: 46180.667 | C172: 46180.67 | D172: anonymous | E172: 46180 | F172: Saharin bin Rotan | G172: 12000069 | H172: (BRE) Brunei Rotary Engineering | I172: Electrical technician | J172: Site Office First Floor | K172: Safe Act or Positive Practice (An appreciation to be made to that person who shows good examples) / Kelakuan yang Baik | L172: Cleaner doing the cleaning and put the signage's on the entrance so people aware there is cleaning activity | N172: Keep up your good works and it inspire me to keep my office tidy | O172: Proactive Approach / Teguran Positif (Safe Act / Positive Act) | P172: Done | Q172: {=_xlfn.XLOOKUP(Table4[[#This Row],[Full Name / Nama Penuh]],Table1[[#All],[Employee Name]],Table1[[#All],[Status]],"",0,1)} -> Active
A173: 7140 | B173: 46191.265 | C173: 46191.272 | D173: anonymous | E173: 46179 | F173: Muhd Hishamuddin bin Edis Asmena | G173: 12000088 | H173: (BRE) Brunei Rotary Engineering | I173: Instrument Technician Shift | J173: Site Office's Staffs Rest Area | K173: Unsafe Act (Dangerous or Unsafe Act that was done by someone) / Perbuatan Bahaya | L173: Several bicycles were found parked in the site cabin area. It was noted that some bicycles had missing parts, suspected to have been stolen by unknown person (unauthorized removal). | M173: if no action is taken could be stated as: -Continued theft of bicycle parts or entire bicycles, resulting in further property losses. -Reduced employee morale and trust due to concerns about personal property security. | N173: -Install CCTV cameras or improve surveillance coverage around the bicycle parking area. -Enhance lighting in the site cabin area to improve visibility, especially during non-working hours. -Encourage bicycle owners to use locks and secure their bicycles properly. -Conduct regular security patrols and inspections of the parking area. | O173: Individual Behaviour / Tingkah Laku yang Cuai dan Berbahaya | P173: Done | Q173: {=_xlfn.XLOOKUP(Table4[[#This Row],[Full Name / Nama Penuh]],Table1[[#All],[Employee Name]],Table1[[#All],[Status]],"",0,1)} -> Active
A174: 7050 | B174: 46178.46 | C174: 46178.466 | D174: anonymous | E174: 46178 | F174: Ahmed Abdelfattah Ahmed Aly Shaaban | G174: 12000019 | H174: (BRE) Brunei Rotary Engineering | I174: Urea rotating lead | J174: Urea Plant | K174: Unsafe Condition (Dangerous Area that has potential to cause harm or injury to People within the Area) / Keadaan Bahaya | L174: Acid leak from acid dosing unit to ground , a lot of chemical mats used to absorb and containment but no prober house keeping for these mats frequently until leak repair done. | M174: Acid covering the ground area , where all operation and maintenance doing activities | N174: Informed site operator to ask thier contractor ( brudesh) to do prober house keeping for the area and disposal for the mats full of acid and to inform environment team | O174: Hazardous - Unsafe Materials / Benda yang Berbahaya | P174: Done | Q174: {=_xlfn.XLOOKUP(Table4[[#This Row],[Full Name / Nama Penuh]],Table1[[#All],[Employee Name]],Table1[[#All],[Status]],"",0,1)} -> Active
A175: 7054 | B175: 46179.31 | C175: 46179.314 | D175: anonymous | E175: 46178 | F175: Abu bakar ali | G175: 12000234 | H175: (BRE) Brunei Rotary Engineering | I175: Welder | J175: Urea Plant | K175: Unsafe Condition (Dangerous Area that has potential to cause harm or injury to People within the Area) / Keadaan Bahaya | L175: Open hole scaffolding floor. | M175: Somebody will fall to the hole and can get serious injury. | N175: Call scaffolding supv for immediately close the hole. | O175: Hazardous - Unsafe Environment / Situasi Tempat Kerja yang Berbahaya untuk Alam Sekitar | P175: Not BRE | Q175: {=_xlfn.XLOOKUP(Table4[[#This Row],[Full Name / Nama Penuh]],Table1[[#All],[Employee Name]],Table1[[#All],[Status]],"",0,1)}
A176: 7053 | B176: 46179.297 | C176: 46179.302 | D176: anonymous | E176: 46178 | F176: Abu bakar ali | G176: 12000234 | H176: (BRE) Brunei Rotary Engineering | I176: Welder | J176: Workshop | K176: Unsafe Act (Dangerous or Unsafe Act that was done by someone) / Perbuatan Bahaya | L176: During grinding the spark are pointing to other workers. | M176: Flying spark can cause eye injury. | N176: Stop the worker, change the direction and grinding positions to other side which no body around that area. | O176: Position of People / Keberadaan seseorang ketika bekerja (Line of Fire, Drop Object & Slip, Trip and Fall) | P176: Not BRE | Q176: {=_xlfn.XLOOKUP(Table4[[#This Row],[Full Name / Nama Penuh]],Table1[[#All],[Employee Name]],Table1[[#All],[Status]],"",0,1)}
A177: 7051 | B177: 46178.467 | C177: 46178.472 | D177: anonymous | E177: 46178 | F177: Ahmed Abdelfattah Ahmed Aly Shaaban | G177: 12000019 | H177: (BRE) Brunei Rotary Engineering | I177: Urea rotating lead | J177: Urea Plant | K177: Safe Act or Positive Practice (An appreciation to be made to that person who shows good examples) / Kelakuan yang Baik | L177: Prober handling & disposal for oil after maintenance activities completion by urea rotating team | M177: Non prober handling and disposal will lead to oil spillage, slip& trip wich may lead to injury | N177: Appreciated the urea rotating team effort and encouraged for keep the same practice | O177: Hazardous - Unsafe Materials / Benda yang Berbahaya | P177: Done | Q177: {=_xlfn.XLOOKUP(Table4[[#This Row],[Full Name / Nama Penuh]],Table1[[#All],[Employee Name]],Table1[[#All],[Status]],"",0,1)} -> Active
A178: 7049 | B178: 46178.456 | C178: 46178.459 | D178: anonymous | E178: 46178 | F178: Muhammad Ali Shafie Bin Haji Ali Sabahrin | G178: 12000148 | H178: (BRE) Brunei Rotary Engineering | I178: Welder | J178: Workshop | K178: Safe Act or Positive Practice (An appreciation to be made to that person who shows good examples) / Kelakuan yang Baik | L178: I've seen my supervisor is doing a material preparation for next week task. | M178: - Work stops mid-task: You get halfway and realize you’re missing wire, fittings, or fasteners. Job stalls until procurement delivers - Schedule slips: Waiting on materials pushes deadlines and affects other teams that depend on you - Rush orders & higher cost: Last-minute buys mean paying express shipping or premium prices - Wrong substitutes used: People grab “close enough” materials to keep moving. That risks quality, performance, or safety - Idle time for the crew: Techs stand around or get pulled to low-value work. Morale and productivity drop - Rework later: If wrong or substandard materials were used to save time, you’ll redo the job later - Poor coordination: Other teams, contractors, or vendors show up ready but can’t proceed. Creates friction between departments - Safety gaps: Improvising with wrong materials in electrical/mechanical work increases incident risk | N178: - Review next week’s job list every Friday: Sit 10 min with the team/supervisor and list what’s needed for each task - Check stock vs. plan: Walk the store and compare BOM/material list to what’s on hand. Flag shortages early - Use a simple material prep checklist: Include item, qty, location, and who checks it. Post it near the job board - Raise PR/MR early: Submit requests by Friday morning so procurement and store have time to react - Pre-kitting: Pull and stage all materials for each job in a labeled bin/trolley. Monday starts with “grab and go” - Confirm with other teams: Quick check with instrument, electrical, mechanical that they’ve got what they need too - Assign ownership: Make one person responsible for prep and follow-up, not “everyone” - Log common shortages: Track what’s always missing and push for buffer stock or faster re-order points - Do a 5-min handover: End of Friday, confirm what’s ready and what’s pending. No surprises Monday morning | O178: Proactive Approach / Teguran Positif (Safe Act / Positive Act) | P178: Done | Q178: {=_xlfn.XLOOKUP(Table4[[#This Row],[Full Name / Nama Penuh]],Table1[[#All],[Employee Name]],Table1[[#All],[Status]],"",0,1)} -> Active
A179: 7048 | B179: 46178.441 | C179: 46178.445 | D179: anonymous | E179: 46178 | F179: Suebsak Mahintarathep | G179: 12000141 | H179: (BRE) Brunei Rotary Engineering | I179: Mechanical Maintenance supervisor | J179: Workshop | K179: Safe Act or Positive Practice (An appreciation to be made to that person who shows good examples) / Kelakuan yang Baik | L179: Workshop team do fabrication new pipe spool , after they cut they keep pipe material on ground near working area | M179: They can slip & trip form pipe spools | N179: I inform them to move pipe spools out from working area | O179: Hazardous - Unsafe Materials / Benda yang Berbahaya | P179: Done | Q179: {=_xlfn.XLOOKUP(Table4[[#This Row],[Full Name / Nama Penuh]],Table1[[#All],[Employee Name]],Table1[[#All],[Status]],"",0,1)} -> Active
A180: 7046 | B180: 46178.384 | C180: 46178.396 | D180: anonymous | E180: 46178 | F180: Muhammad Ali Shafie Bin Haji Ali Sabahrin | G180: 12000148 | H180: (BRE) Brunei Rotary Engineering | I180: Welder | J180: Workshop | K180: Safe Act or Positive Practice (An appreciation to be made to that person who shows good examples) / Kelakuan yang Baik | L180: Doing housekeeping before having off day during the weekend. | M180: - Trip and fall hazards: Tools, cables, offcuts left out become risks when people rush back in Monday morning 🚶‍♂️ - Fire risk: Oily rags, dust, flammable offcuts left near power sources or heat can smolder unattended - Equipment damage: Dust, metal swarf, and coolant get into machines and control panels, causing faults or seizure - Pest problems: Food scraps and waste attract rats, cockroaches, and ants over the weekend - Lost/misplaced tools: Messy benches make it easy to lose items, so Monday starts with hunting instead of working - Corrosion and spoilage: Metal parts left dirty or wet start rusting. Materials get contaminated or unusable - Safety audit failures: Messy workshop = non-compliance with HSE standards. Fines or stop-work orders possible - Lower morale: Coming back to a messy space kills motivation and makes people less careful - Hidden damage: Leaks, cracks, or worn parts stay hidden under debris until they become bigger problems Bottom line: 15 min of housekeeping Friday saves you time, money, and safety headaches on Monday | N180: - Use a 5-min end-of-shift checklist: Post a simple list by the exit/DB: clear benches, store tools, bin waste, wipe machines, check for leaks - Assign “last man out”: Rotate the role so one person does a quick walkthrough and signs off. No guessing who’s responsible - Make it visible: Use shadow boards and labeled storage so putting things back takes 10 sec, not 2 min - Keep cleaning tools handy: Brooms, bins, rags, degreaser within arm’s reach. If it’s far, it won’t get used - Tie it to safety: Start toolbox talks with near-misses from poor housekeeping. Makes the “why” obvious - Supervisors check and reinforce: A quick “thanks, area looks good” goes further than scolding. Recognition builds habit - Do a Friday 15-min push: Block 15 min before knock-off for everyone to clean their zone. Treat it like part of the job, not overtime - Make it a handover item: If the next shift finds a mess, log it. If it’s clean, log that too. Accountability works both ways - Remove excuses: Provide enough bins, storage, and disposal routes so people don’t leave stuff “just for now” Bottom line: When housekeeping is quick, visible, and owned by the crew, it stops being a chore and becomes the way you leave the place. | O180: Proactive Approach / Teguran Positif (Safe Act / Positive Act) | P180: Done | Q180: {=_xlfn.XLOOKUP(Table4[[#This Row],[Full Name / Nama Penuh]],Table1[[#All],[Employee Name]],Table1[[#All],[Status]],"",0,1)} -> Active
A181: 7067 | B181: 46181.496 | C181: 46181.499 | D181: anonymous | E181: 46177 | F181: Muhamad Aqhari bin Jamudin | G181: 12000034 | H181: (BRE) Brunei Rotary Engineering | I181: Technician | J181: Urea Plant | K181: Unsafe Condition (Dangerous Area that has potential to cause harm or injury to People within the Area) / Keadaan Bahaya | L181: Found rubbish on main screen floor at granulation | M181: Unwanted pest like rat could appeared | N181: Throw the rubbish to appropriate bin | O181: Waste Management / Berkaitan dengan Pengurusan Pembuangan Sampah | P181: Done | Q181: {=_xlfn.XLOOKUP(Table4[[#This Row],[Full Name / Nama Penuh]],Table1[[#All],[Employee Name]],Table1[[#All],[Status]],"",0,1)} -> Active
A182: 7099 | B182: 46184.463 | C182: 46184.469 | D182: anonymous | E182: 46177 | F182: Asnie Bin Idris | G182: 12000161 | H182: (BRE) Brunei Rotary Engineering | I182: DE Technician | J182: Jetty Head | K182: Unsafe Condition (Dangerous Area that has potential to cause harm or injury to People within the Area) / Keadaan Bahaya | L182: requires proper housekeeping around the EDG area | M182: if want to check and emergency start the generator engine it is difficult to access the engine area | N182: inform ops to do proper house keeping | O182: Material Arrangement and Housekeeping / Kesesuaian Penyusunan Barang dan Kebersihan Tempat Pekerjaan | P182: Done | Q182: {=_xlfn.XLOOKUP(Table4[[#This Row],[Full Name / Nama Penuh]],Table1[[#All],[Employee Name]],Table1[[#All],[Status]],"",0,1)} -> Active
A183: 7165 | B183: 46191.666 | C183: 46191.677 | D183: anonymous | E183: 46177 | F183: Mohd Habibullah bin Mohd Adnan Izan | G183: 12000131 | H183: (BRE) Brunei Rotary Engineering | I183: Instrument Shift Technician | J183: Ammonia Plant | K183: Safe Act or Positive Practice (An appreciation to be made to that person who shows good examples) / Kelakuan yang Baik | L183: One of the Control Valve has Ammonia Liquid Leak at the gland packing. Required to be tighten. | M183: After the permit was done. If I just go and tighen the gland packing without specific PPEs and without any information of the media on the pipeline. I would expose myself to the Ammonia Liquid. As it was also strong smell of Ammonia around the area. | N183: I discussed with the Operation Team and the Safety Officer. The task required to wear the specific PPEs, such as Chemical gloves, Goggles and Gas Respirator. I wore the speficic PPEs before performing the task. | O183: Hazardous - Unsafe Materials / Benda yang Berbahaya | P183: Done | Q183: {=_xlfn.XLOOKUP(Table4[[#This Row],[Full Name / Nama Penuh]],Table1[[#All],[Employee Name]],Table1[[#All],[Status]],"",0,1)} -> Active
A184: 7164 | B184: 46191.643 | C184: 46191.643 | D184: anonymous | E184: 46177 | F184: Muhammad Akmal Muntaqim bin Haji Bakeri | G184: 12000102 | H184: (BRE) Brunei Rotary Engineering | I184: Mechanical Technician | J184: Warehouse | K184: Improvement Suggestions / Cadangan untuk diperbaiki | L184: Observed theres no enough ventilation at granulation house at screen shaker area | M184: Fatigue, headaches, severe allergy or asthma flareup | N184: Inspect exhaust and dust extraction system or make an open window or door for the airway | O184: Design and Engineering / Tempat Pekerjaan kurang sesuai | P184: Done | Q184: {=_xlfn.XLOOKUP(Table4[[#This Row],[Full Name / Nama Penuh]],Table1[[#All],[Employee Name]],Table1[[#All],[Status]],"",0,1)} -> Active
... A212: 6942 | B212: 46171.299 | C212: 46171.301 | D212: anonymous | E212: 46171 | F212: Nurul Ainul Hayat bin Abdul Majid | G212: 12000097 | H212: (BRE) Brunei Rotary Engineering | I212: Rotating Technician | J212: Offsite & Utilities | K212: Unsafe Condition (Dangerous Area that has potential to cause harm or injury to People within the Area) / Keadaan Bahaya | L212: Mainhole open space nearby cooling water pump | M212: Fall inside mainhole | N212: Provide barricade and immediately provide cover mainhole | O212: Signage and Barriers / Papan Tanda dan Perbatasan Keselamatan tempat kerja | P212: Done | Q212: {=_xlfn.XLOOKUP(Table4[[#This Row],[Full Name / Nama Penuh]],Table1[[#All],[Employee Name]],Table1[[#All],[Status]],"",0,1)} -> Inactive
A213: 6946 | B213: 46171.353 | C213: 46171.355 | D213: anonymous | E213: 46171 | F213: Mahindra patil | H213: (BRE) Brunei Rotary Engineering | I213: Static technician | J213: Jetty Head | K213: Unsafe Condition (Dangerous Area that has potential to cause harm or injury to People within the Area) / Keadaan Bahaya | L213: Platform bolt missing | M213: Slip trip fall | N213: Please inform to workshop team install missing bolts | O213: Design and Engineering / Tempat Pekerjaan kurang sesuai | P213: Done | Q213: {=_xlfn.XLOOKUP(Table4[[#This Row],[Full Name / Nama Penuh]],Table1[[#All],[Employee Name]],Table1[[#All],[Status]],"",0,1)} -> Active
A214: 6952 | B214: 46171.394 | C214: 46171.397 | D214: anonymous | E214: 46171 | F214: Mohd Syahmi Bin Jamalluddin | G214: 12000137 | H214: (BRE) Brunei Rotary Engineering | I214: Instrument Technician | J214: Ammonia Plant | K214: Unsafe Act (Dangerous or Unsafe Act that was done by someone) / Perbuatan Bahaya | L214: The person going up the stairs without holding the handrails | M214: That person may fall and get injured | N214: Approached the person nicely and tell them to hold the handrails to prevent injuries if they slip | O214: Individual Behaviour / Tingkah Laku yang Cuai dan Berbahaya | P214: Done | Q214: {=_xlfn.XLOOKUP(Table4[[#This Row],[Full Name / Nama Penuh]],Table1[[#All],[Employee Name]],Table1[[#All],[Status]],"",0,1)} -> Active
A215: 6964 | B215: 46171.447 | C215: 46171.45 | D215: anonymous | E215: 46171 | F215: Mohammad Raimi bin Mohammad | G215: 12000070 | H215: (BRE) Brunei Rotary Engineering | I215: Electrical Shift Technician | J215: Plant Entry Gate | K215: Unsafe Act (Dangerous or Unsafe Act that was done by someone) / Perbuatan Bahaya | L215: driver didnt follow the designated roundabout and drove straight instead circulating in right direction. | M215: car accident | N215: advice the driver to follow the correct roundabout route | O215: Individual Behaviour / Tingkah Laku yang Cuai dan Berbahaya | P215: Done | Q215: {=_xlfn.XLOOKUP(Table4[[#This Row],[Full Name / Nama Penuh]],Table1[[#All],[Employee Name]],Table1[[#All],[Status]],"",0,1)} -> Active
A216: 6974 | B216: 46171.711 | C216: 46171.712 | D216: anonymous | E216: 46171 | F216: Nur Muhammad Bin Awang Kasim | G216: 12000125 | H216: (BRE) Brunei Rotary Engineering | I216: Technician | J216: Unsure / Kurang Pasti | K216: Unsafe Act (Dangerous or Unsafe Act that was done by someone) / Perbuatan Bahaya | L216: Reckless driving | M216: Accident | N216: Tell the driver to drive more carefully | O216: Individual Behaviour / Tingkah Laku yang Cuai dan Berbahaya | P216: Done | Q216: {=_xlfn.XLOOKUP(Table4[[#This Row],[Full Name / Nama Penuh]],Table1[[#All],[Employee Name]],Table1[[#All],[Status]],"",0,1)} -> Active
A217: 6976 | B217: 46172.083 | C217: 46172.093 | D217: anonymous | E217: 46171 | F217: Abu bakar ali | G217: 12000234 | H217: (BRE) Brunei Rotary Engineering | I217: Welder | J217: Ammonia Storage Tank Area | K217: Unsafe Condition (Dangerous Area that has potential to cause harm or injury to People within the Area) / Keadaan Bahaya | L217: Scaffolding inspection tag expired | M217: Some body will use that scaffolding without be inspected by scaffolding supv, afraid some modifications made by the other workers using it. | N217: Always check the tags before use the scaffolding for safety reasons. | O217: Position of People / Keberadaan seseorang ketika bekerja (Line of Fire, Drop Object & Slip, Trip and Fall) | P217: Not BRE | Q217: {=_xlfn.XLOOKUP(Table4[[#This Row],[Full Name / Nama Penuh]],Table1[[#All],[Employee Name]],Table1[[#All],[Status]],"",0,1)}
A218: 6987 | B218: 46173.558 | C218: 46173.56 | D218: anonymous | E218: 46171 | F218: Liyana Abd Rahim | G218: 12000035 | H218: (BRE) Brunei Rotary Engineering | I218: Electrical Technician | J218: Urea Plant | K218: Unsafe Condition (Dangerous Area that has potential to cause harm or injury to People within the Area) / Keadaan Bahaya | L218: Ammonia Smell but no signage seen in the area | M218: Many people will inhale the smell | N218: Put barricade | O218: Hazardous - Unsafe Environment / Situasi Tempat Kerja yang Berbahaya untuk Alam Sekitar | P218: Done | Q218: {=_xlfn.XLOOKUP(Table4[[#This Row],[Full Name / Nama Penuh]],Table1[[#All],[Employee Name]],Table1[[#All],[Status]],"",0,1)} -> Active
A219: 6943 | B219: 46171.335 | C219: 46171.337 | D219: anonymous | E219: 46171 | F219: Mohamed Aizzudin Bin Awang Haji Tuah | G219: 12000075 | H219: (BRE) Brunei Rotary Engineering | I219: Workshop technician | J219: HSSE Office | K219: Safe Act or Positive Practice (An appreciation to be made to that person who shows good examples) / Kelakuan yang Baik | L219: Good presentation by HSE team | M219: Nil | N219: Congrats the team | O219: Communication / Kurang Perbincangan waktu Bekerja, Kurang Permahaman Arahan atau Kurang Pengetahuan Bahasa Asing | P219: Done | Q219: {=_xlfn.XLOOKUP(Table4[[#This Row],[Full Name / Nama Penuh]],Table1[[#All],[Employee Name]],Table1[[#All],[Status]],"",0,1)} -> Active
A220: 6962 | B220: 46171.442 | C220: 46171.445 | D220: anonymous | E220: 46171 | F220: Ram Pratap Nishad | G220: 12000056 | H220: (BRE) Brunei Rotary Engineering | I220: Senior Static Technician | J220: Ammonia Plant | K220: Safe Act or Positive Practice (An appreciation to be made to that person who shows good examples) / Kelakuan yang Baik | L220: Filter strainer cleaning 1051F008A&B, both filter cleaning done one by one after proper isolation, drained and cooled down... | M220: Good working behaviour and coordination between all technicians.. proper positive working behaviour.. | N220: Good working behaviour | O220: Proactive Approach / Teguran Positif (Safe Act / Positive Act) | P220: Done | Q220: {=_xlfn.XLOOKUP(Table4[[#This Row],[Full Name / Nama Penuh]],Table1[[#All],[Employee Name]],Table1[[#All],[Status]],"",0,1)} -> Active
A221: 6967 | B221: 46171.395 | C221: 46171.475 | D221: anonymous | E221: 46171 | F221: Zayar Tun | G221: 12000168 | H221: (BRE) Brunei Rotary Engineering | I221: SUPERVISOR | J221: Offsite & Utilities | K221: Safe Act or Positive Practice (An appreciation to be made to that person who shows good examples) / Kelakuan yang Baik | L221: Good Housekeeping | M221: Can be happen no save | N221: Good actions | O221: Material Arrangement and Housekeeping / Kesesuaian Penyusunan Barang dan Kebersihan Tempat Pekerjaan | P221: Done | Q221: {=_xlfn.XLOOKUP(Table4[[#This Row],[Full Name / Nama Penuh]],Table1[[#All],[Employee Name]],Table1[[#All],[Status]],"",0,1)} -> Active
A222: 6968 | B222: 46171.479 | C222: 46171.479 | D222: anonymous | E222: 46171 | F222: Muhammad Akmal Muntaqim bin Haji Bakeri | G222: 12000102 | H222: (BRE) Brunei Rotary Engineering | I222: Mechanical Technician | J222: Offsite & Utilities | K222: Safe Act or Positive Practice (An appreciation to be made to that person who shows good examples) / Kelakuan yang Baik | L222: Observed mechanical team did housekeeping after finished work | M222: NA | N222: Good job | O222: Material Arrangement and Housekeeping / Kesesuaian Penyusunan Barang dan Kebersihan Tempat Pekerjaan | P222: Done | Q222: {=_xlfn.XLOOKUP(Table4[[#This Row],[Full Name / Nama Penuh]],Table1[[#All],[Employee Name]],Table1[[#All],[Status]],"",0,1)} -> Active
A223: 6933 | B223: 46170.833 | C223: 46170.835 | D223: anonymous | E223: 46170 | F223: Muhammad Rashid bin Harun | G223: 12000063 | H223: (BRE) Brunei Rotary Engineering | I223: Electrical Technician | J223: Plant Entry Gate | K223: Unsafe Act (Dangerous or Unsafe Act that was done by someone) / Perbuatan Bahaya | L223: A personnel was entering the plant without safety glasses. | M223: He could get injured if anh incident happen | N223: I intervene and told him to wear his safety glasses and he comply | O223: Personal Protective Equipment / Pemakaian Alat Pelindung Diri | P223: Done | Q223: {=_xlfn.XLOOKUP(Table4[[#This Row],[Full Name / Nama Penuh]],Table1[[#All],[Employee Name]],Table1[[#All],[Status]],"",0,1)} -> Active
A224: 6975 | B224: 46171.712 | C224: 46171.713 | D224: anonymous | E224: 46170 | F224: Nur Muhammad Bin Awang Kasim | G224: 12000125 | H224: (BRE) Brunei Rotary Engineering | I224: Technician | J224: Unsure / Kurang Pasti | K224: Unsafe Act (Dangerous or Unsafe Act that was done by someone) / Perbuatan Bahaya | L224: Reckless driving | M224: Accident | N224: Tell the driver to driver more carefully | O224: Individual Behaviour / Tingkah Laku yang Cuai dan Berbahaya | P224: Done | Q224: {=_xlfn.XLOOKUP(Table4[[#This Row],[Full Name / Nama Penuh]],Table1[[#All],[Employee Name]],Table1[[#All],[Status]],"",0,1)} -> Active
A225: 6932 | B225: 46170.829 | C225: 46170.831 | D225: anonymous | E225: 46170 | F225: Muhammad Rashid bin Harun | G225: 12000063 | H225: (BRE) Brunei Rotary Engineering | I225: Electrical Technician | J225: Site Office First Floor | K225: Safe Act or Positive Practice (An appreciation to be made to that person who shows good examples) / Kelakuan yang Baik | L225: My Team has work safely for the whole month in MAy | M225: can become complacent in safety matter | N225: I praise and encourage them to keep up being safe | O225: Proactive Approach / Teguran Positif (Safe Act / Positive Act) | P225: Done | Q225: {=_xlfn.XLOOKUP(Table4[[#This Row],[Full Name / Nama Penuh]],Table1[[#All],[Employee Name]],Table1[[#All],[Status]],"",0,1)} -> Active
... A237: 6896 | B237: 46168.411 | C237: 46168.417 | D237: anonymous | E237: 46168 | F237: Mohamed Khalil Ashalla Bagdad | G237: 12000010 | H237: (BRE) Brunei Rotary Engineering | I237: RE &SE Section Manager | J237: Ammonia Plant | K237: Unsafe Condition (Dangerous Area that has potential to cause harm or injury to People within the Area) / Keadaan Bahaya | L237: Ammonia vents and drains project Many lines near to ground in the walkway need to protected against the walkers Some steps to convert them with proper painting and warning signs | M237: Damage of the lines and injuries for the operators | N237: Raising the card to HSSE | O237: Signage and Barriers / Papan Tanda dan Perbatasan Keselamatan tempat kerja | P237: Done | Q237: {=_xlfn.XLOOKUP(Table4[[#This Row],[Full Name / Nama Penuh]],Table1[[#All],[Employee Name]],Table1[[#All],[Status]],"",0,1)} -> Active
A238: 6901 | B238: 46168.476 | C238: 46168.478 | D238: anonymous | E238: 46168 | F238: Shamiza binti Hussin | G238: 12000025 | H238: (BRE) Brunei Rotary Engineering | I238: Electrical Technician | J238: Jetty Modules Area | K238: Unsafe Condition (Dangerous Area that has potential to cause harm or injury to People within the Area) / Keadaan Bahaya | L238: An exit signage is hanging | M238: May fall off and hit somebody | N238: Fix the signage | O238: Facility Management / Perawatan Kemudahan dan Aset | P238: Done | Q238: {=_xlfn.XLOOKUP(Table4[[#This Row],[Full Name / Nama Penuh]],Table1[[#All],[Employee Name]],Table1[[#All],[Status]],"",0,1)} -> Active | R238: Yes
A239: 6904 | B239: 46168.566 | C239: 46168.575 | D239: anonymous | E239: 46168 | F239: Nurzahirulhaq Mostar Bin Shafiee | G239: 12000147 | H239: (BRE) Brunei Rotary Engineering | I239: Pipefitter | J239: Urea Plant | K239: Unsafe Condition (Dangerous Area that has potential to cause harm or injury to People within the Area) / Keadaan Bahaya | L239: a contractor was observed carrying out scaffolding erection activities without proper barricading | M239: This unsafe condition may lead to potential falling object incidents, which could result in serious injury to personnel passing below the scaffolding work area | N239: Contractor personnel were advised to stop work temporarily and advise to install proper barrication. | O239: Signage and Barriers / Papan Tanda dan Perbatasan Keselamatan tempat kerja | P239: Done | Q239: {=_xlfn.XLOOKUP(Table4[[#This Row],[Full Name / Nama Penuh]],Table1[[#All],[Employee Name]],Table1[[#All],[Status]],"",0,1)} -> Active
A240: 6905 | B240: 46168.581 | C240: 46168.581 | D240: anonymous | E240: 46168 | F240: Nurzahirulhaq Mostar Bin Shafiee | G240: 12000147 | H240: (BRE) Brunei Rotary Engineering | I240: Pipefitter | J240: Offsite & Utilities | K240: Unsafe Act (Dangerous or Unsafe Act that was done by someone) / Perbuatan Bahaya | L240: a fellow colleague was observed carrying out work activities alone without a designated partner or buddy system in place. | M240: This condition may expose the worker to increased risk in the event of an emergency, injury, sudden illness, or unsafe situation, as there would be no immediate assistance or communication support available. | N240: I accompanied and monitored him throughout the task until the work was completed safely. I advised him on the importance of complying with the buddy system requirement and encouraged to bring a partner/helper even though the task could be carried out by one person | O240: Proactive Approach / Teguran Positif (Safe Act / Positive Act) | P240: Done | Q240: {=_xlfn.XLOOKUP(Table4[[#This Row],[Full Name / Nama Penuh]],Table1[[#All],[Employee Name]],Table1[[#All],[Status]],"",0,1)} -> Active
A241: 6906 | B241: 46168.594 | C241: 46168.598 | D241: anonymous | E241: 46168 | F241: Mohammad Hazieduddin bin Hussin | G241: BRE 12000066 | H241: (BRE) Brunei Rotary Engineering | I241: Electrical Technician (Shift) | J241: Electrical Substation | K241: Unsafe Act (Dangerous or Unsafe Act that was done by someone) / Perbuatan Bahaya | L241: A working personal almost trip while climbing up the stairs. | M241: Severe injury from the trip and fatality can occur from the fall. | N241: Intervene and advice the working personal to climb the stairs carefully and mindful of his steps. | O241: Position of People / Keberadaan seseorang ketika bekerja (Line of Fire, Drop Object & Slip, Trip and Fall) | P241: Done | Q241: {=_xlfn.XLOOKUP(Table4[[#This Row],[Full Name / Nama Penuh]],Table1[[#All],[Employee Name]],Table1[[#All],[Status]],"",0,1)} -> Active
A242: 6908 | B242: 46168.612 | C242: 46168.619 | D242: anonymous | E242: 46168 | F242: M. Fazill Bin Awang Hj Sulaiman | G242: 12000115 | H242: (BRE) Brunei Rotary Engineering | I242: Static Technician | J242: North Building Ground Floor | K242: Unsafe Condition (Dangerous Area that has potential to cause harm or injury to People within the Area) / Keadaan Bahaya | L242: There is no light for entrance/exit near the north building when I work night shift, hard to see the path way and have a lot bicycle and tricycle near the building cluttered. | M242: fall slip and trip | N242: need to improve the lighting | O242: Design and Engineering / Tempat Pekerjaan kurang sesuai | P242: Done | Q242: {=_xlfn.XLOOKUP(Table4[[#This Row],[Full Name / Nama Penuh]],Table1[[#All],[Employee Name]],Table1[[#All],[Status]],"",0,1)} -> Active
A243: 6909 | B243: 46168.619 | C243: 46168.622 | D243: anonymous | E243: 46168 | F243: M. Fazill Bin Awang Hj Sulaiman | G243: 12000115 | H243: (BRE) Brunei Rotary Engineering | I243: Static Technician | J243: Unsure / Kurang Pasti | K243: Unsafe Act (Dangerous or Unsafe Act that was done by someone) / Perbuatan Bahaya | L243: I found tools at site was left unattended. | M243: Tools missing and will be hard for the tools owner. | N243: I kept the tools with me and searched for the owner tools. | O243: Material Arrangement and Housekeeping / Kesesuaian Penyusunan Barang dan Kebersihan Tempat Pekerjaan | P243: Done | Q243: {=_xlfn.XLOOKUP(Table4[[#This Row],[Full Name / Nama Penuh]],Table1[[#All],[Employee Name]],Table1[[#All],[Status]],"",0,1)} -> Active
A244: 6917 | B244: 46168.694 | C244: 46168.696 | D244: anonymous | E244: 46168 | F244: Muhd Nur Khairul Ikram Bin Mohd Warith | G244: 12000122 | H244: (BRE) Brunei Rotary Engineering | I244: Shift Instrument Technician | J244: Ammonia Plant | K244: Unsafe Condition (Dangerous Area that has potential to cause harm or injury to People within the Area) / Keadaan Bahaya | L244: We were about to enter noise area in NH3 plant. | M244: Could cause ear discomfort. | N244: Before entering the area, we stopped and put on our earplug before we proceed. | O244: Hazardous - Unsafe Environment / Situasi Tempat Kerja yang Berbahaya untuk Alam Sekitar | P244: Done | Q244: {=_xlfn.XLOOKUP(Table4[[#This Row],[Full Name / Nama Penuh]],Table1[[#All],[Employee Name]],Table1[[#All],[Status]],"",0,1)} -> Active
A245: 6920 | B245: 46168.937 | C245: 46168.938 | D245: anonymous | E245: 46168 | F245: Muhammad Harriz Hazwan Bin Abdullah Tegong | G245: 12000164 | H245: (BRE) Brunei Rotary Engineering | I245: Senior Scaffolder | J245: Ammonia Plant | K245: Unsafe Act (Dangerous or Unsafe Act that was done by someone) / Perbuatan Bahaya | L245: I have been saw someone was walking at ammonia (compressor house) area without wearing any ear protection because their is high level noise during normal operation of plant. | M245: It's can cause of losing of hearing due to high level noise area. | N245: I do approach & stop that personnel and am also doing intervention him to stay away from high level noise area to avoid of hearing been affective which can lead to deaf. | O245: Individual Behaviour / Tingkah Laku yang Cuai dan Berbahaya | P245: Done | Q245: {=_xlfn.XLOOKUP(Table4[[#This Row],[Full Name / Nama Penuh]],Table1[[#All],[Employee Name]],Table1[[#All],[Status]],"",0,1)} -> Active
A246: 6966 | B246: 46171.464 | C246: 46171.467 | D246: anonymous | E246: 46168 | F246: Muhammad Akmal Muntaqim bin Haji Bakeri | G246: 12000102 | H246: (BRE) Brunei Rotary Engineering | I246: Mechanical Technician | J246: Ammonia Storage Tank Area | K246: Unsafe Condition (Dangerous Area that has potential to cause harm or injury to People within the Area) / Keadaan Bahaya | L246: Observed someone shoe lace tuck out. | M246: Slip, Trip & Fall | N246: Informed him to tie his shoe lace. | O246: Position of People / Keberadaan seseorang ketika bekerja (Line of Fire, Drop Object & Slip, Trip and Fall) | P246: Done | Q246: {=_xlfn.XLOOKUP(Table4[[#This Row],[Full Name / Nama Penuh]],Table1[[#All],[Employee Name]],Table1[[#All],[Status]],"",0,1)} -> Active
A247: 6900 | B247: 46168.473 | C247: 46168.476 | D247: anonymous | E247: 46168 | F247: Dk NoorFaszalenna Pg Zaini | G247: 12000024 | H247: (BRE) Brunei Rotary Engineering | I247: Electrical Technician | J247: Jetty Modules Area | K247: Improvement Suggestions / Cadangan untuk diperbaiki | L247: Door Exit signage is not properly installed ( almost fell off) | M247: - | N247: Should be properly installed so that the exit door is known and better labelled | O247: Facility Management / Perawatan Kemudahan dan Aset | P247: Done | Q247: {=_xlfn.XLOOKUP(Table4[[#This Row],[Full Name / Nama Penuh]],Table1[[#All],[Employee Name]],Table1[[#All],[Status]],"",0,1)} -> Active
A248: 6902 | B248: 46168.487 | C248: 46168.493 | D248: anonymous | E248: 46168 | F248: Mohammad Nabil Haji Gapor | G248: 12000044 | H248: (BRE) Brunei Rotary Engineering | I248: Lead Electrical Technician | J248: Urea Plant | K248: Safe Act or Positive Practice (An appreciation to be made to that person who shows good examples) / Kelakuan yang Baik | L248: there is empty bottle found on the floor | M248: trip and fall | N248: pick the bottle and throw it at recycle bin. | O248: Waste Management / Berkaitan dengan Pengurusan Pembuangan Sampah | P248: Done | Q248: {=_xlfn.XLOOKUP(Table4[[#This Row],[Full Name / Nama Penuh]],Table1[[#All],[Employee Name]],Table1[[#All],[Status]],"",0,1)} -> Active
A249: 6912 | B249: 46168.634 | C249: 46168.634 | D249: anonymous | E249: 46168 | F249: Muhammad Ali Shafie Bin Haji Ali Sabahrin | G249: 12000148 | H249: (BRE) Brunei Rotary Engineering | I249: Welder | J249: Warehouse | K249: Safe Act or Positive Practice (An appreciation to be made to that person who shows good examples) / Kelakuan yang Baik | L249: Doing a Positive material identification on materials that we just order. To make sure the material stainless steel it is the right identification. | M249: - Wrong grade installed: carbon steel or low-grade stainless gets used instead, leading to rapid corrosion and failure - Premature leaks/failure: wrong alloy can’t handle the process fluid, temp, or pressure it was designed for - Costly rework: you have to shut down, cut out, and replace piping, flanges, or vessels after startup - Safety hazard: failure under pressure can cause burns, chemical release, or mechanical injury - Weld issues: wrong grade welds poorly, cracks, or fails NDT later - Audit/non-compliance: fails QA/QC, client specs, and regulatory requirements like ASME/ISO - Warranty void: supplier and insurer reject claims if material isn’t verified as ordered - Contamination risk: mixing grades in a process line can contaminate product or cause galvanic corrosion - Lost time tracking it down: you waste hours investigating why equipment is failing instead of working | N249: - *Make PMI mandatory in the work pack*: List it as a hold point in the ITP before install starts - *Check at goods receiving*: Don’t accept material into stores until PMI is done and matched to the MTC - *Use certified equipment*: Only use calibrated PMI guns/XRF devices with trained, authorized personnel - *Mark and record*: Tag every item tested and log results with heat/lot number in the material register - *Quarantine untested items*: Physically segregate material that hasn’t passed PMI to prevent mix-ups - *Spot check traceability*: Verify heat numbers on material match the test certificates and PMI results - *Involve QC/QA*: Get independent sign-off on critical lines, pressure parts, and alloy systems - *Communicate findings fast*: If a mismatch is found, stop work and raise an NCR immediately - *Train the crew*: Make sure fitters, welders, and supervisors know why PMI matters and what to look for - *Review trends*: Track PMI failures to catch supplier issues early and tighten procurement | O249: Proactive Approach / Teguran Positif (Safe Act / Positive Act) | P249: Done | Q249: {=_xlfn.XLOOKUP(Table4[[#This Row],[Full Name / Nama Penuh]],Table1[[#All],[Employee Name]],Table1[[#All],[Status]],"",0,1)} -> Active
A250: 6913 | B250: 46168.638 | C250: 46168.644 | D250: anonymous | E250: 46168 | F250: Muhammad Ali Shafie Bin Haji Ali Sabahrin | G250: 12000148 | H250: (BRE) Brunei Rotary Engineering | I250: Welder | J250: BFI SPARK, Car Park C (Big Space) | K250: Safe Act or Positive Practice (An appreciation to be made to that person who shows good examples) / Kelakuan yang Baik | L250: During weekdays my colleague always invited us to go for a jogg or running for 30mins to 1 hr. To make sure to maintain our fitness. | M250: - Lower stamina on the job: Gets tired faster during shutdowns, overtime, and physical tasks - Higher injury risk: Weaker core, legs, and joints make strains, slips, and back issues more likely - Weight gain & metabolic issues: Less calorie burn + stress snacking = weight gain, higher risk of diabetes, BP problems - Poor sleep quality: No physical fatigue means restless nights and feeling groggy the next day - Higher stress & irritability: Misses the natural stress release from exercise, so tension builds up - Weaker immune system: Less active people catch colds and take longer to recover - Reduced focus: Less blood flow and endorphins means slower reaction time and poorer decision making on site - Lower morale: Feels sluggish and unmotivated, which drags on team energy | N250: - Schedule it like a meeting: Block 30-60 min after work in the calendar so it doesn’t get bumped by “just one more task” - Make it social: Jog, gym, or walk with a colleague. Peer pressure keeps you accountable and makes it more fun - keep gear ready: Leave running shoes, gym clothes, or a skipping rope in your bag/car so there’s no excuse - Start small and build up: 20 min walk > no activity. Consistency beats intensity for long-term fitness - *lMix it up: Rotate jogging, cycling, bodyweight workouts, sports. Boredom kills routines - Set simple goals: Track steps, distance, or time. Seeing progress keeps motivation up - Use downtime smartly: If stuck on site, do stretching, bodyweight circuits, or a quick walk around the workshop - Get supervisor buy-in: If management encourages post-shift fitness, it becomes part of site culture - Link it to job benefits: Remind yourself it cuts injury risk, boosts stamina for shutdowns, and improves sleep - Avoid all-or-nothing mindset: Missed a day? Just restart next day. Don’t let one miss kill the habit | O250: Proactive Approach / Teguran Positif (Safe Act / Positive Act) | P250: Done | Q250: {=_xlfn.XLOOKUP(Table4[[#This Row],[Full Name / Nama Penuh]],Table1[[#All],[Employee Name]],Table1[[#All],[Status]],"",0,1)} -> Active
A251: 6916 | B251: 46168.68 | C251: 46168.682 | D251: anonymous | E251: 46168 | F251: Mohammad Syukri Bin Safri | G251: 12000036 | H251: (BRE) Brunei Rotary Engineering | I251: Electrical Technician | J251: Electrical Substation | K251: Improvement Suggestions / Cadangan untuk diperbaiki | L251: Tag blocked by MCB switch inside panel | M251: Could isolate wrong tag number if not improve or change the position of the tag | N251: Reported to substation team | O251: Design and Engineering / Tempat Pekerjaan kurang sesuai | P251: Done | Q251: {=_xlfn.XLOOKUP(Table4[[#This Row],[Full Name / Nama Penuh]],Table1[[#All],[Employee Name]],Table1[[#All],[Status]],"",0,1)} -> Active
A252: 6919 | B252: 46168.898 | C252: 46168.911 | D252: anonymous | E252: 46168 | F252: Muhammad Harriz Hazwan Bin Abdullah Tegong | G252: 12000164 | H252: (BRE) Brunei Rotary Engineering | I252: Senior Scaffolder | J252: Offsite & Utilities | K252: Safe Act or Positive Practice (An appreciation to be made to that person who shows good examples) / Kelakuan yang Baik | L252: I have seen our third party contractor doing properly housekeeping of scaffolding materials at work site area. | M252: N/A | N252: It's good practice (housekeeping) for any individual workers who performing any such as of activities on site (plant) area,which is it helping to minimize of slip,trip & fall hazard from happening. | O252: Material Arrangement and Housekeeping / Kesesuaian Penyusunan Barang dan Kebersihan Tempat Pekerjaan | P252: Done | Q252: {=_xlfn.XLOOKUP(Table4[[#This Row],[Full Name / Nama Penuh]],Table1[[#All],[Employee Name]],Table1[[#All],[Status]],"",0,1)} -> Active
A253: 6940 | B253: 46171.289 | C253: 46171.293 | D253: anonymous | E253: 46168 | F253: Perhatian Piara Ginting | G253: 12000047 | H253: (BRE) Brunei Rotary Engineering | I253: Sr Rotating Technician | J253: Cooling Tower Area | K253: Safe Act or Positive Practice (An appreciation to be made to that person who shows good examples) / Kelakuan yang Baik | L253: Used stair handrail during up and down to cooling tower fan area | M253: To avoid falling down | N253: Good safety | O253: Proactive Approach / Teguran Positif (Safe Act / Positive Act) | P253: Done | Q253: {=_xlfn.XLOOKUP(Table4[[#This Row],[Full Name / Nama Penuh]],Table1[[#All],[Employee Name]],Table1[[#All],[Status]],"",0,1)} -> Active
A254: 6973 | B254: 46171.5 | C254: 46171.503 | D254: anonymous | E254: 46168 | F254: Ram Pratap Nishad | G254: 12000056 | H254: (BRE) Brunei Rotary Engineering | I254: Senior Static Technician | J254: Ammonia Plant | K254: Safe Act or Positive Practice (An appreciation to be made to that person who shows good examples) / Kelakuan yang Baik | L254: Pump 1821P003B suction strainer cleaning work.. | M254: Proper isolation of suction and discharge valve electrical isolation certificate drain and vent..done before start work .. | N254: Safe working behaviour | O254: Individual Behaviour / Tingkah Laku yang Cuai dan Berbahaya | P254: Done | Q254: {=_xlfn.XLOOKUP(Table4[[#This Row],[Full Name / Nama Penuh]],Table1[[#All],[Employee Name]],Table1[[#All],[Status]],"",0,1)} -> Active
A255: 6863 | B255: 46167.464 | C255: 46167.465 | D255: anonymous | E255: 46167 | F255: Mohd Khairun Nazhem Mohd Husaini | G255: 12000138 | H255: (BRE) Brunei Rotary Engineering | I255: Inst Eng. | J255: Ammonia Plant | K255: Unsafe Act (Dangerous or Unsafe Act that was done by someone) / Perbuatan Bahaya | L255: Personnel standing below scaffolding where personnel working above is mobilizing material (piping) | M255: falling objects, injuries to person standing below, death | N255: remind personnel to keep away from line of fire, area to be barricaded during mobilizing material | O255: Position of People / Keberadaan seseorang ketika bekerja (Line of Fire, Drop Object & Slip, Trip and Fall) | P255: Done | Q255: {=_xlfn.XLOOKUP(Table4[[#This Row],[Full Name / Nama Penuh]],Table1[[#All],[Employee Name]],Table1[[#All],[Status]],"",0,1)} -> Active | R255: Yes
A256: 6864 | B256: 46167.467 | C256: 46167.467 | D256: anonymous | E256: 46167 | F256: Mohd Khairun Nazhem Mohd Husaini | G256: 12000138 | H256: (BRE) Brunei Rotary Engineering | I256: Inst Eng. | J256: Urea Plant | K256: Unsafe Act (Dangerous or Unsafe Act that was done by someone) / Perbuatan Bahaya | L256: Personnel not wearing safety harness on scaffold at a height | M256: fall, slip, trip | N256: Remind personnel of working at height safety practices | O256: Personal Protective Equipment / Pemakaian Alat Pelindung Diri | P256: Done | Q256: {=_xlfn.XLOOKUP(Table4[[#This Row],[Full Name / Nama Penuh]],Table1[[#All],[Employee Name]],Table1[[#All],[Status]],"",0,1)} -> Active | R256: Yes
A257: 6869 | B257: 46167.599 | C257: 46167.602 | D257: anonymous | E257: 46167 | F257: Jessica Menyie Anak Kabuary | G257: 12000030 | H257: (BRE) Brunei Rotary Engineering | I257: ELECTRICAL TECHNICIAN | J257: Product Handling | K257: Unsafe Condition (Dangerous Area that has potential to cause harm or injury to People within the Area) / Keadaan Bahaya | L257: There is a cable tray found between a running vibrating motors. | M257: The cable tray can damage the running motor if the pointy part of the cable tray come in contact with the motor. | N257: Remove the cable tray to the side and inform supervisor. | O257: Material Arrangement and Housekeeping / Kesesuaian Penyusunan Barang dan Kebersihan Tempat Pekerjaan | P257: Done | Q257: {=_xlfn.XLOOKUP(Table4[[#This Row],[Full Name / Nama Penuh]],Table1[[#All],[Employee Name]],Table1[[#All],[Status]],"",0,1)} -> Active
A258: 6885 | B258: 46167.613 | C258: 46167.616 | D258: anonymous | E258: 46167 | F258: Dk NoorFaszalenna Pg Zaini | G258: 12000024 | H258: (BRE) Brunei Rotary Engineering | I258: Electrical Technician | J258: Offsite & Utilities | K258: Unsafe Act (Dangerous or Unsafe Act that was done by someone) / Perbuatan Bahaya | L258: A personnel was carrying long ladder and accidentally hit his head. Thankfully he is wearing his safety helmet. But he should wear the helmet chin strap so that the helmet is more secure. | M258: He might hit his head again and maybe his helmet fall off if he is not using the chinstrap | N258: Stop him and asked him to use chinstrap just in case he hit his head again | O258: Individual Behaviour / Tingkah Laku yang Cuai dan Berbahaya | P258: Done | Q258: {=_xlfn.XLOOKUP(Table4[[#This Row],[Full Name / Nama Penuh]],Table1[[#All],[Employee Name]],Table1[[#All],[Status]],"",0,1)} -> Active | R258: Yes
A259: 6886 | B259: 46167.623 | C259: 46167.625 | D259: anonymous | E259: 46167 | F259: Asnie Bin Idris | G259: 12000161 | H259: (BRE) Brunei Rotary Engineering | I259: DE Technician | J259: Offsite & Utilities | K259: Unsafe Act (Dangerous or Unsafe Act that was done by someone) / Perbuatan Bahaya | L259: forklift carrying ibc tank at speed | M259: can cause the ibc tank to fall | N259: tell the forklift operator to slow down | O259: Individual Behaviour / Tingkah Laku yang Cuai dan Berbahaya | P259: Done | Q259: {=_xlfn.XLOOKUP(Table4[[#This Row],[Full Name / Nama Penuh]],Table1[[#All],[Employee Name]],Table1[[#All],[Status]],"",0,1)} -> Active
A260: 6888 | B260: 46167.596 | C260: 46167.648 | D260: anonymous | E260: 46167 | F260: Shamiza binti Hussin | G260: 12000025 | H260: (BRE) Brunei Rotary Engineering | I260: Electrical Technician | J260: Product Handling | K260: Unsafe Act (Dangerous or Unsafe Act that was done by someone) / Perbuatan Bahaya | L260: A personnel not using handrail while taking the stairs as the staircase is slippery | M260: He mau slip, trip and fall | N260: Ask them to hold the handrail while using the staircase | O260: Individual Behaviour / Tingkah Laku yang Cuai dan Berbahaya | P260: Done | Q260: {=_xlfn.XLOOKUP(Table4[[#This Row],[Full Name / Nama Penuh]],Table1[[#All],[Employee Name]],Table1[[#All],[Status]],"",0,1)} -> Active | R260: Yes
A261: 6889 | B261: 46167.632 | C261: 46167.652 | D261: anonymous | E261: 46167 | F261: Muhammed Abeed Bin Sarkawi | G261: 12000031 | H261: (BRE) Brunei Rotary Engineering | I261: Electrical Engineering | J261: Product Handling | K261: Unsafe Condition (Dangerous Area that has potential to cause harm or injury to People within the Area) / Keadaan Bahaya | L261: poor housekeeping. steel structure laid on the floor with its ends poking out unkept. | M261: Trip and fall, and possibly stabbing injuries might occur. | N261: After confirming no activities involved the steel structure, it was immediately removed from site and disposed of properly. | O261: Individual Behaviour / Tingkah Laku yang Cuai dan Berbahaya | P261: Done | Q261: {=_xlfn.XLOOKUP(Table4[[#This Row],[Full Name / Nama Penuh]],Table1[[#All],[Employee Name]],Table1[[#All],[Status]],"",0,1)} -> Active
A262: 6890 | B262: 46167.676 | C262: 46167.678 | D262: anonymous | E262: 46167 | F262: Mohammad Kamil Hakimin Mohd Amin | G262: 12000089 | H262: (BRE) Brunei Rotary Engineering | I262: Rotating Technician Level 1 | J262: Ammonia Plant | K262: Unsafe Act (Dangerous or Unsafe Act that was done by someone) / Perbuatan Bahaya | L262: not using a proper hand glove when dealing with oil | M262: glove might get wet by oil | N262: use proper glove | O262: Individual Behaviour / Tingkah Laku yang Cuai dan Berbahaya | P262: Done | Q262: {=_xlfn.XLOOKUP(Table4[[#This Row],[Full Name / Nama Penuh]],Table1[[#All],[Employee Name]],Table1[[#All],[Status]],"",0,1)} -> Active | R262: Yes
A263: 6891 | B263: 46167.679 | C263: 46167.681 | D263: anonymous | E263: 46167 | F263: Muhd Nur Khairul Ikram Bin Mohd Warith | G263: 12000122 | H263: (BRE) Brunei Rotary Engineering | I263: Shift Instrument Technician | J263: Ammonia Plant | K263: Unsafe Act (Dangerous or Unsafe Act that was done by someone) / Perbuatan Bahaya | L263: Saw my colleague haven't put on his earplug when we were about to enter loud noise area | M263: Could cause ear discomfort | N263: Both of us stopped and told him to put on his earplug first before proceed. | O263: Personal Protective Equipment / Pemakaian Alat Pelindung Diri | P263: Done | Q263: {=_xlfn.XLOOKUP(Table4[[#This Row],[Full Name / Nama Penuh]],Table1[[#All],[Employee Name]],Table1[[#All],[Status]],"",0,1)} -> Active
A264: 6915 | B264: 46168.679 | C264: 46168.681 | D264: anonymous | E264: 46167 | F264: Muhammad Nabil Bin Haji Misli | G264: 12000028 | H264: (BRE) Brunei Rotary Engineering | I264: Electrical Technician | J264: Jetty Head | K264: Unsafe Condition (Dangerous Area that has potential to cause harm or injury to People within the Area) / Keadaan Bahaya | L264: Ground floor stairs to Substation 4, have water inside building and need housekeeping | M264: Slip, trip and fall | N264: Informed supervisor | O264: Material Arrangement and Housekeeping / Kesesuaian Penyusunan Barang dan Kebersihan Tempat Pekerjaan | P264: Done | Q264: {=_xlfn.XLOOKUP(Table4[[#This Row],[Full Name / Nama Penuh]],Table1[[#All],[Employee Name]],Table1[[#All],[Status]],"",0,1)} -> Active
A265: 6865 | B265: 46167.594 | C265: 46167.597 | D265: anonymous | E265: 46167 | F265: Yusde Bin Junaidi | G265: 12000149 | H265: (BRE) Brunei Rotary Engineering | I265: Workshop Technician | J265: Workshop | K265: Improvement Suggestions / Cadangan untuk diperbaiki | L265: Waste disposal skid request to be moved a little closer to workshop area for easier waste disposal | M265: As the skid is too far it is very hard to dispose of waste materials each time due to the waste sometimes is in large quantities | N265: Move the skid closer | O265: Waste Management / Berkaitan dengan Pengurusan Pembuangan Sampah | P265: Done | Q265: {=_xlfn.XLOOKUP(Table4[[#This Row],[Full Name / Nama Penuh]],Table1[[#All],[Employee Name]],Table1[[#All],[Status]],"",0,1)} -> Active
A266: 6866 | B266: 46167.597 | C266: 46167.599 | D266: anonymous | E266: 46167 | F266: Muhamad Aqhari bin Jamudin | G266: 12000034 | H266: (BRE) Brunei Rotary Engineering | I266: Technician | J266: Urea Plant | K266: Safe Act or Positive Practice (An appreciation to be made to that person who shows good examples) / Kelakuan yang Baik | L266: Use proper tools when adjusting lighting fixture | M266: Pinch point | N266: Use proper tools | O266: Tools, Equipment and Machinery / Berkaitan dengan Alat Kegunaan Pekerjaan dan Mesin sama ada ianya Tidak Sesuai untuk aktivitas tersebut atau sebaliknya | P266: Done | Q266: {=_xlfn.XLOOKUP(Table4[[#This Row],[Full Name / Nama Penuh]],Table1[[#All],[Employee Name]],Table1[[#All],[Status]],"",0,1)} -> Active
A267: 6892 | B267: 46167.67 | C267: 46167.684 | D267: anonymous | E267: 46167 | F267: Mohamed Khalil Ashalla Bagdad | G267: 12000010 | H267: (BRE) Brunei Rotary Engineering | I267: Re and Se manager | J267: Urea Plant | K267: Improvement Suggestions / Cadangan untuk diperbaiki | L267: Ventilation system need to be implemented in granulation unit | M267: Working at the area for long time affects on operation and maintenance people | N267: Communicated with technical team | O267: Design and Engineering / Tempat Pekerjaan kurang sesuai | P267: Done | Q267: {=_xlfn.XLOOKUP(Table4[[#This Row],[Full Name / Nama Penuh]],Table1[[#All],[Employee Name]],Table1[[#All],[Status]],"",0,1)} -> Active
A268: 6893 | B268: 46167.761 | C268: 46167.769 | D268: anonymous | E268: 46167 | F268: Mohd Habibullah bin Mohd Adnan Izan | G268: 12000131 | H268: (BRE) Brunei Rotary Engineering | I268: Instrument Technician (Shift) | J268: Site Office's Staffs Rest Area | K268: Improvement Suggestions / Cadangan untuk diperbaiki | L268: One of the Surau fan is not working quite a long time. | M268: The fan(s) is to circulate the air surrounding. The heat trapped in the surau especially during the dry season. | N268: I would like to suggest, do preventive maintenance for all the necessity. | O268: Facility Management / Perawatan Kemudahan dan Aset | P268: Done | Q268: {=_xlfn.XLOOKUP(Table4[[#This Row],[Full Name / Nama Penuh]],Table1[[#All],[Employee Name]],Table1[[#All],[Status]],"",0,1)} -> Active
A269: 6850 | B269: 46166.27 | C269: 46166.277 | D269: anonymous | E269: 46166 | F269: Muhd Hishamuddin bin Edis Asmena | G269: 12000088 | H269: (BRE) Brunei Rotary Engineering | I269: Instrument Technician Shift | J269: Jetty Head | K269: Unsafe Condition (Dangerous Area that has potential to cause harm or injury to People within the Area) / Keadaan Bahaya | L269: Several lamps on the shiploader are currently inoperative. | M269: -Reduced visibility for operators and maintenance. -Difficulty seeing moving parts, walkways, ladders, and transfer points. Increased chance of slips, trips, and falls. | N269: Suggestions: -Install temporary lighting. -Restrict night operations in poorly lit zones. -Barricade dark areas. -Prioritize lamp replacement/repair. -Conduct pre-use lighting inspection before operation. | O269: Hazardous - Unsafe Materials / Benda yang Berbahaya | P269: Done | Q269: {=_xlfn.XLOOKUP(Table4[[#This Row],[Full Name / Nama Penuh]],Table1[[#All],[Employee Name]],Table1[[#All],[Status]],"",0,1)} -> Active
A270: 6851 | B270: 46166.284 | C270: 46166.284 | D270: anonymous | E270: 46166 | F270: Muhd Hishamuddin bin Edis Asmena | G270: 12000088 | H270: (BRE) Brunei Rotary Engineering | I270: Instrument Technician Shift | J270: Ammonia Plant | K270: Unsafe Condition (Dangerous Area that has potential to cause harm or injury to People within the Area) / Keadaan Bahaya | L270: Several unit areas were found with accumulated residual rainwater due to inadequate drainage. | M270: Creating potential slip, trip, and fall hazard. | N270: Suggestions: -Drain and remove all accumulated rainwater immediately. -Improve drainage system to prevent water stagnation. -Conduct regular housekeeping and area inspections, especially after rainfall. -Place warning signage and barricades at affected areas until conditions are safe. | O270: Hazardous - Unsafe Environment / Situasi Tempat Kerja yang Berbahaya untuk Alam Sekitar | P270: Done | Q270: {=_xlfn.XLOOKUP(Table4[[#This Row],[Full Name / Nama Penuh]],Table1[[#All],[Employee Name]],Table1[[#All],[Status]],"",0,1)} -> Active
A271: 6925 | B271: 46169.505 | C271: 46169.509 | D271: anonymous | E271: 46166 | F271: Hamizan bin Rahman | G271: 12000140 | H271: (BRE) Brunei Rotary Engineering | I271: Lead Shift Instrument Technician | J271: CCR | K271: Unsafe Act (Dangerous or Unsafe Act that was done by someone) / Perbuatan Bahaya | L271: An individual was observed on their way to the control room area from site office , without wearing the safety helmet | M271: Head injury from falling or moving objects | N271: Verbal and safety reminder provided to the individual | O271: Individual Behaviour / Tingkah Laku yang Cuai dan Berbahaya | P271: Done | Q271: {=_xlfn.XLOOKUP(Table4[[#This Row],[Full Name / Nama Penuh]],Table1[[#All],[Employee Name]],Table1[[#All],[Status]],"",0,1)} -> Active
A272: 6957 | B272: 46171.419 | C272: 46171.42 | D272: anonymous | E272: 46166 | F272: Galant Putra | G272: 12000077 | H272: (BRE) Brunei Rotary Engineering | I272: sr instrument engineer | J272: Jetty Head | K272: Safe Act or Positive Practice (An appreciation to be made to that person who shows good examples) / Kelakuan yang Baik | L272: there was bypass job for the damage instrumentation at shiploader2. Prior to that, the team had prepared the bypass form and approved with the related parties | M272: if no documentation and proper approval it will violate the LSR. And with the documentation, the OP can prepare future mitigation of the risk | N272: Appreciate the team for the action | O272: Proactive Approach / Teguran Positif (Safe Act / Positive Act) | P272: Done | Q272: {=_xlfn.XLOOKUP(Table4[[#This Row],[Full Name / Nama Penuh]],Table1[[#All],[Employee Name]],Table1[[#All],[Status]],"",0,1)} -> Active
A273: 6924 | B273: 46169.498 | C273: 46169.502 | D273: anonymous | E273: 46165 | F273: Hamizan bin Rahman | G273: 12000140 | H273: (BRE) Brunei Rotary Engineering | I273: Lead Shift Instrument Technician | J273: Car Park near North Building | K273: Unsafe Act (Dangerous or Unsafe Act that was done by someone) / Perbuatan Bahaya | L273: An individuals operating vehicles at excessive speed within the designated car park area | M273: Risk of collision with pedestrians & increased likelihood of vehicle-to-vehicle accidents | N273: Supervisors/security personnel were informed regarding the incident | O273: Individual Behaviour / Tingkah Laku yang Cuai dan Berbahaya | P273: Done | Q273: {=_xlfn.XLOOKUP(Table4[[#This Row],[Full Name / Nama Penuh]],Table1[[#All],[Employee Name]],Table1[[#All],[Status]],"",0,1)} -> Active
A274: 6844 | B274: 46164.498 | C274: 46164.5 | D274: anonymous | E274: 46164 | F274: Vinod Kumar Verma | G274: 12000050 | H274: (BRE) Brunei Rotary Engineering | I274: Rotating technician | J274: Workshop | K274: Unsafe Condition (Dangerous Area that has potential to cause harm or injury to People within the Area) / Keadaan Bahaya | L274: Lot of scarp material workshop outside | M274: slip trip fall | N274: please romove scrap shift to scarp yard | O274: Hazardous - Unsafe Materials / Benda yang Berbahaya | P274: Done | Q274: {=_xlfn.XLOOKUP(Table4[[#This Row],[Full Name / Nama Penuh]],Table1[[#All],[Employee Name]],Table1[[#All],[Status]],"",0,1)} -> Active
... A280: 6880 | B280: 46167.607 | C280: 46167.61 | D280: anonymous | E280: 46163 | F280: Muhammad Asadullah Rizvi | G280: 12000049 | H280: (BRE) Brunei Rotary Engineering | I280: Sr rotating technician | J280: Urea Plant | K280: Unsafe Act (Dangerous or Unsafe Act that was done by someone) / Perbuatan Bahaya | L280: Doring replace the motor 1271P013A the Rigger manual lifting the motor 2nd floor | M280: Havey moto if fell down may be some one serious injury | N280: Used carne | O280: Manual Handling / Cara Mengangkat Benda | P280: Done | Q280: {=_xlfn.XLOOKUP(Table4[[#This Row],[Full Name / Nama Penuh]],Table1[[#All],[Employee Name]],Table1[[#All],[Status]],"",0,1)} -> Active
A281: 6883 | B281: 46167.61 | C281: 46167.613 | D281: anonymous | E281: 46163 | F281: Muhammad Asadullah Rizvi | G281: 12000049 | H281: (BRE) Brunei Rotary Engineering | I281: Sr rotating technician | J281: Urea Plant | K281: Unsafe Act (Dangerous or Unsafe Act that was done by someone) / Perbuatan Bahaya | L281: 1271P013A During the replaced motor Rigger used scaffolding this scaffolding have red tag | M281: Falling objects they don't used safety harness | N281: They waiting the complete the scaffolding and inspection then used | O281: Individual Behaviour / Tingkah Laku yang Cuai dan Berbahaya | P281: Done | Q281: {=_xlfn.XLOOKUP(Table4[[#This Row],[Full Name / Nama Penuh]],Table1[[#All],[Employee Name]],Table1[[#All],[Status]],"",0,1)} -> Active | R281: Yes
A282: 6827 | B282: 46163.354 | C282: 46163.356 | D282: anonymous | E282: 46163 | F282: Mohd Shaari Bin Salleh | G282: 12000048 | H282: (BRE) Brunei Rotary Engineering | I282: Rotating Supervisor | J282: Urea Plant | K282: Improvement Suggestions / Cadangan untuk diperbaiki | L282: No ventilation provided at 8 floors of granulation area | M282: People exhausted due to restricted air circulation during maintenance. The temperature raised and the ambient become not convenient during work execution | N282: inform to take frequently rest if exhausted | O282: Design and Engineering / Tempat Pekerjaan kurang sesuai | P282: Done | Q282: {=_xlfn.XLOOKUP(Table4[[#This Row],[Full Name / Nama Penuh]],Table1[[#All],[Employee Name]],Table1[[#All],[Status]],"",0,1)} -> Active
A283: 6829 | B283: 46163.362 | C283: 46163.365 | D283: anonymous | E283: 46163 | F283: Mohd Shaari Bin Salleh | G283: 12000048 | H283: (BRE) Brunei Rotary Engineering | I283: Rotating Supervisor | J283: Compressor Unit Area | K283: Improvement Suggestions / Cadangan untuk diperbaiki | L283: oil spillage from Used oil collector | M283: Possibly of slip, trip and fall due to slippery area and make the area dirty. | N283: Provide temporary barricade | O283: Material Arrangement and Housekeeping / Kesesuaian Penyusunan Barang dan Kebersihan Tempat Pekerjaan | P283: Done | Q283: {=_xlfn.XLOOKUP(Table4[[#This Row],[Full Name / Nama Penuh]],Table1[[#All],[Employee Name]],Table1[[#All],[Status]],"",0,1)} -> Active
A284: 6838 | B284: 46163.504 | C284: 46163.652 | D284: anonymous | E284: 46163 | F284: Muhammad Ali Shafie Bin Haji Ali Sabahrin | G284: 12000148 | H284: (BRE) Brunei Rotary Engineering | I284: Welder | J284: Workshop | K284: Safe Act or Positive Practice (An appreciation to be made to that person who shows good examples) / Kelakuan yang Baik | L284: After shutdown activities completed, our superior asking us to make a material inspection and consumables checking. | M284: - Wrong spares on site: you find out too late that gaskets, bolts, or seals don’t fit the equipment - Missing stock: critical consumables like welding rods, oxygen, or cleaning solvent run out mid-job - Wrong specs used: crew grabs whatever is available, leading to leaks, vibration, or premature failure - Rework and delays: equipment gets reassembled with wrong parts and has to be opened again - Cost blowout: emergency purchases and courier fees hit the budget hard - Safety risk: using degraded, expired, or uncertified materials like slings, gloves, or filters - Permit hold-up: job can’t start because material verification is part of PTW closure - Lost tools/materials: nobody knows what was left in the unit or taken back to store - Audit findings: HSSE and QA flag “poor material control” as a root cause in incident reports - Crew frustration: night shift wastes hours hunting for items that should have been checked and staged | N284: - Use a checklist: list every item, spec, and quantity needed before the job starts - Verify against work pack: match gaskets, bolts, valves, and consumables to drawings and MOC - Check physical condition: look for damage, corrosion, expiry dates, and valid certificates - Stage materials early: move everything to the job location before work starts, not mid-task - Account for returns: log what’s used, damaged, or left over so stores stays accurate - Involve QA/QC: get inspection sign-off on critical items before they go into the system - Label everything: tag materials with tag no., spec, and job reference to avoid mix-ups - Control access: keep a responsible person managing issue/return to prevent losses - Do joint verification: crew + supervisor + stores do the check together, not solo - Update records: close out material logs in CMMS/ERP so next job starts with correct stock - Flag shortages early: raise MTO or purchase request as soon as something’s missing, not at T-0 - Review after job: note what was wrong or missing to fix the process next time | O284: Proactive Approach / Teguran Positif (Safe Act / Positive Act) | P284: Done | Q284: {=_xlfn.XLOOKUP(Table4[[#This Row],[Full Name / Nama Penuh]],Table1[[#All],[Employee Name]],Table1[[#All],[Status]],"",0,1)} -> Active
A285: 6873 | B285: 46167.606 | C285: 46167.607 | D285: anonymous | E285: 46163 | F285: Ummi Farhanah bte Zulkifle | G285: 12000029 | H285: (BRE) Brunei Rotary Engineering | I285: Electrical Technician | J285: Cooling Tower Area | K285: Safe Act or Positive Practice (An appreciation to be made to that person who shows good examples) / Kelakuan yang Baik | L285: Colleague wear complete safety harness while working on scaffolding | M285: - | N285: Great practices | O285: Scaffolding and Working at Height / Yang berkaitan dengan Scaffolding dan Bekerja tempat tinggi | P285: Done | Q285: {=_xlfn.XLOOKUP(Table4[[#This Row],[Full Name / Nama Penuh]],Table1[[#All],[Employee Name]],Table1[[#All],[Status]],"",0,1)} -> Active
A286: 6941 | B286: 46171.293 | C286: 46171.296 | D286: anonymous | E286: 46163 | F286: Perhatian Piara Ginting | G286: 12000047 | H286: (BRE) Brunei Rotary Engineering | I286: Senior Rotating Technician | J286: Cooling Tower Area | K286: Safe Act or Positive Practice (An appreciation to be made to that person who shows good examples) / Kelakuan yang Baik | L286: Used body harness during doing calibration motor job | M286: Can falling down from 5 meter | N286: Good safety (PPE) | O286: Personal Protective Equipment / Pemakaian Alat Pelindung Diri | P286: Done | Q286: {=_xlfn.XLOOKUP(Table4[[#This Row],[Full Name / Nama Penuh]],Table1[[#All],[Employee Name]],Table1[[#All],[Status]],"",0,1)} -> Active
A287: 6801 | B287: 46162.022 | C287: 46162.025 | D287: anonymous | E287: 46162 | F287: Mohd Hifdzuramir bin Hj Mohd Zain | G287: 12000130 | H287: (BRE) Brunei Rotary Engineering | I287: Shift instrument supervisor | J287: Urea Plant | K287: Unsafe Condition (Dangerous Area that has potential to cause harm or injury to People within the Area) / Keadaan Bahaya | L287: Observed that the staircase from Ground Level to Level 1 and Level 2 at Urea Granulation was very slippery, including the handrails, due to excessive urea deposits. | M287: If no action is taken, the slippery staircase and handrails may cause personnel to lose footing, resulting in slips, falls, and possible injuries, especially during routine access between levels. | N287: Notified the responsible personnel and requested immediate cleaning of the staircase and handrails to remove urea deposits. Also recommended implementing routine housekeeping and inspection to maintain safe and slip-free access between levels. | O287: Hazardous - Unsafe Environment / Situasi Tempat Kerja yang Berbahaya untuk Alam Sekitar | P287: Done | Q287: {=_xlfn.XLOOKUP(Table4[[#This Row],[Full Name / Nama Penuh]],Table1[[#All],[Employee Name]],Table1[[#All],[Status]],"",0,1)} -> Active
A288: 6816 | B288: 46162.593 | C288: 46162.595 | D288: anonymous | E288: 46162 | F288: Rhea Nurramizah binti Abdullah Bajing | G288: 12000106 | H288: (BRE) Brunei Rotary Engineering | I288: Instrument Engineer | J288: Car Park near Clinic | K288: Unsafe Condition (Dangerous Area that has potential to cause harm or injury to People within the Area) / Keadaan Bahaya | L288: A garden hoe and spade were seen placed between the car parks laying on the ground. | M288: People could trip on these | N288: N/A | O288: Material Arrangement and Housekeeping / Kesesuaian Penyusunan Barang dan Kebersihan Tempat Pekerjaan | P288: Done | Q288: {=_xlfn.XLOOKUP(Table4[[#This Row],[Full Name / Nama Penuh]],Table1[[#All],[Employee Name]],Table1[[#All],[Status]],"",0,1)} -> Active
A289: 6823 | B289: 46162.656 | C289: 46162.663 | D289: anonymous | E289: 46162 | F289: Amal Nurul Fawedda Razali | G289: 12000120 | H289: (BRE) Brunei Rotary Engineering | I289: INSTRUMENT TECHNICIAN | J289: Car Park near North Building | K289: Unsafe Condition (Dangerous Area that has potential to cause harm or injury to People within the Area) / Keadaan Bahaya | L289: Farming tools (large blade and shovel) were observed left unattended in the parking lot. | M289: Trip and Fall Hazard Tools left on the ground in the parking lot can cause personnel to trip and fall, leading to injuries such as sprains or fractures. Injury from Sharp Objects A blade left unattended may cause: Cuts or lacerations Serious injury if stepped on or handled improperly | N289: No person was identified in the area to approach. | O289: Individual Behaviour / Tingkah Laku yang Cuai dan Berbahaya | P289: Done | Q289: {=_xlfn.XLOOKUP(Table4[[#This Row],[Full Name / Nama Penuh]],Table1[[#All],[Employee Name]],Table1[[#All],[Status]],"",0,1)} -> Active
A290: 6836 | B290: 46163.635 | C290: 46163.64 | D290: anonymous | E290: 46162 | F290: Nur Zawani Binti Marrot | G290: 12000111 | H290: (BRE) Brunei Rotary Engineering | I290: Instrument Techinician | J290: Car Park near North Building | K290: Unsafe Condition (Dangerous Area that has potential to cause harm or injury to People within the Area) / Keadaan Bahaya | L290: Observed unattended shovel and a large farming blade were found left openly on the ground without supervision or proper storage. The tools were located in an area accessible to pedestrians and vehicles. | M290: The farming blade was exposed and posed a significant risk of cuts or serious injury. The shovel also created a potential tripping hazard for individuals walking through the parking lot. This can cause risk of cuts or lacerations from exposed blade, trip and fall hazard caused by tools left on walking path, potential vehicle damage if tools are run over, unsafe worksite housekeeping practices, risk of unauthorized handling by visitors or staff. | N290: Ensure all farming tools are properly stored after use. Implement routine inspections of common and parking areas. Remind workers of workplace housekeeping and safety procedures. Store sharp tools with blade covers or inside secured containers. Install warning signage if maintenance or farming activities are ongoing nearby. | O290: Hazardous - Unsafe Environment / Situasi Tempat Kerja yang Berbahaya untuk Alam Sekitar | P290: Done | Q290: {=_xlfn.XLOOKUP(Table4[[#This Row],[Full Name / Nama Penuh]],Table1[[#All],[Employee Name]],Table1[[#All],[Status]],"",0,1)} -> Active
A291: 6804 | B291: 46162.331 | C291: 46162.331 | D291: anonymous | E291: 46162 | F291: Muhammad Ali Shafie Bin Haji Ali Sabahrin | G291: 12000148 | H291: (BRE) Brunei Rotary Engineering | I291: Welder | J291: Workshop | K291: Safe Act or Positive Practice (An appreciation to be made to that person who shows good examples) / Kelakuan yang Baik | L291: Ive seen that my supervisor always before doing any task, he will bring us to do site visits to make plans how do we proceed the task. | M291: - Missed hazards: you walk into open edges, live lines, or confined spaces nobody warned you about - Wrong method used: you start a job with the wrong tools or sequence because you didn’t see the site - Underestimated work: task takes 2x longer because access, height, or obstacles weren’t checked - Wrong materials ordered: wrong size flanges, bolts, or scaffolding show up on site - Permit errors: JSA and PTW get written for the wrong location or conditions, making them useless - Rework and delays: you demo or install in the wrong spot and have to redo it - Safety system gaps: no barricades, gas testing, or fire watch set up because nobody knew it was needed - Crew confusion: everyone does different things because there’s no clear step-by-step plan - Higher injury risk: rushing and guessing leads to slips, strains, and dropped objects - Equipment damage: you hit buried lines, cable trays, or live equipment you didn’t know existed - Client pushback: quality fails inspection because it wasn’t built to actual site conditions - Audit findings: HSSE flags “lack of planning” and “inadequate supervision” as root causes | N291: - Do a walkdown with the crew: let the people doing the job see the actual area and hazards - Check access and egress: confirm how to get tools, materials, and people in/out safely - Identify live energy: mark electrical, pressure, chemical, and hot surfaces before writing JSA - Measure twice: take real dimensions for materials, scaffolding, and clearance instead of guessing - Talk to ops/maintenance: ask what changed since last job and what’s hidden behind panels - Match method to site: choose the right equipment and steps for the actual space and conditions - Write the JSA on site: build controls around real hazards you can see, not office assumptions - Confirm permits: make sure PTW matches the location, scope, and controls from the walkdown - Check resources: verify you have enough manpower, tools, PPE, and time for the job - Plan barricades and signage: decide where to set them before work starts to keep others out - Share the plan: brief everyone in TBT so no one starts guessing or doing their own thing - Document findings: take photos and notes during visit so you can reference them later - Review after execution: note what worked and what didn’t to improve the next plan | O291: Proactive Approach / Teguran Positif (Safe Act / Positive Act) | P291: Done | Q291: {=_xlfn.XLOOKUP(Table4[[#This Row],[Full Name / Nama Penuh]],Table1[[#All],[Employee Name]],Table1[[#All],[Status]],"",0,1)} -> Active
A292: 6811 | B292: 46162.49 | C292: 46162.493 | D292: anonymous | E292: 46162 | F292: Mohamed Abdelrahman Mohamed Goumaa | G292: 12000107 | H292: (BRE) Brunei Rotary Engineering | I292: Instrument O&U Supervisor | J292: Unsure / Kurang Pasti | K292: Safe Act or Positive Practice (An appreciation to be made to that person who shows good examples) / Kelakuan yang Baik | L292: Hot weather, bring water to the site if working for long period. | M292: dehydration , heatstroke | N292: to remind people to always bring water to site/working for long period of time especially when exposed to direct sunlight | O292: Proactive Approach / Teguran Positif (Safe Act / Positive Act) | P292: Done | Q292: {=_xlfn.XLOOKUP(Table4[[#This Row],[Full Name / Nama Penuh]],Table1[[#All],[Employee Name]],Table1[[#All],[Status]],"",0,1)} -> Active
A293: 6812 | B293: 46162.494 | C293: 46162.497 | D293: anonymous | E293: 46162 | F293: Mohamed Abdelrahman Mohamed Goumaa | G293: 12000107 | H293: (BRE) Brunei Rotary Engineering | I293: Instrument O&U Supervisor | J293: Unsure / Kurang Pasti | K293: Safe Act or Positive Practice (An appreciation to be made to that person who shows good examples) / Kelakuan yang Baik | L293: damaged car tire | M293: can cause the car loss control and balance, safety also affected especially when driving fast. | N293: to always check tire before using the car. to always follow the speed limits when driving. if found damaged to change it immediately. | O293: Proactive Approach / Teguran Positif (Safe Act / Positive Act) | P293: Done | Q293: {=_xlfn.XLOOKUP(Table4[[#This Row],[Full Name / Nama Penuh]],Table1[[#All],[Employee Name]],Table1[[#All],[Status]],"",0,1)} -> Active
... A300: 6793 | B300: 46161.587 | C300: 46161.59 | D300: anonymous | E300: 46161 | F300: Asnie Bin Idris | G300: 12000161 | H300: (BRE) Brunei Rotary Engineering | I300: DE Technician | J300: Offsite & Utilities | K300: Unsafe Act (Dangerous or Unsafe Act that was done by someone) / Perbuatan Bahaya | L300: Not wearing gloves when doing hammering to stud bolts | M300: can be slippery to hold a hammer | N300: Ask to wear impact gloves when hammering stud bolts | O300: Personal Protective Equipment / Pemakaian Alat Pelindung Diri | P300: Done | Q300: {=_xlfn.XLOOKUP(Table4[[#This Row],[Full Name / Nama Penuh]],Table1[[#All],[Employee Name]],Table1[[#All],[Status]],"",0,1)} -> Active
...

Sheet CARE Card KPI Value
B1: Pillar | C1: KPI Name | D1: KPI Definition | E1: 2025 | Q1: 2026
E2: 25-Apr | F2: 25-May | G2: 25-Jun | H2: Q2 | I2: 25-Jul | J2: 25-Aug | K2: 25-Sep | L2: Q3 | M2: 25-Oct | N2: 25-Nov | O2: 25-Dec | P2: Q4 | Q2: 26-Jan | R2: 26-Feb | S2: 26-Mar | T2: Q1 | U2: 26-Apr | V2: 26-May | W2: 46199 | X2: Q2 | Y2: 46229 | Z2: 46260 | AA2: 46291 | AB2: Q3 | AC2: 46321 | AD2: 46352 | AE2: 46382 | AF2: Q4
B3: HSE | C3: Total Number of CARE Cards (Monthly) | D3: KPI Guideline | E3: 184 | F3: 182 | G3: 137 | H3: =SUM(E3:G3) -> 503 | I3: 351 | J3: 351 | K3: 201 | L3: =SUM(I3:K3) -> 903 | M3: 464 | N3: 259 | O3: 218 | P3: 482 | Q3: 100 | R3: 98 | S3: 173 | T3: 566 | U3: 234 | V3: 197 | W3: 169 | X3: 665 | Y3: 242 | Z3: 242 | AA3: 242 | AB3: 726 | AC3: 242 | AD3: 242 | AE3: 242 | AF3: 726
C4: Number of Employees (Monthly) | E4: 151 | F4: 151 | G4: 151 | H4: 151 | I4: 151 | J4: 151 | K4: 151 | L4: 151 | M4: 151 | N4: 148 | O4: 121 | P4: 121 | Q4: 121 | R4: 121 | S4: 121 | T4: 121 | U4: 121 | V4: 122 | W4: 121 | X4: 115 | Y4: 121 | Z4: 121 | AA4: 121 | AB4: 121 | AC4: 121 | AD4: 121 | AE4: 121 | AF4: 121
C5: Number of CARE Cards per Employee (Monthly) | E5: =MIN(E3/E4,2) -> 1.218543 | F5: =MIN(F3/F4,2) -> 1.205298 | G5: =MIN(G3/G4,2) -> 0.90728477 | H5: =MIN(H3/(H4*3),2) -> 1.1103753 | I5: =MIN(I3/I4,2) -> 2 | J5: =MIN(J3/J4,2) -> 2 | K5: =MIN(K3/K4,2) -> 1.3311258 | L5: =MIN(L3/(L4*3),2) -> 1.9933775 | M5: =MIN(M3/M4,2) -> 2 | N5: =MIN(N3/N4,2) -> 1.75 | O5: =MIN(O3/O4,2) -> 1.8016529 | P5: =MIN(P3/(P4*3),2) -> 1.3278237 | Q5: =MIN(Q3/Q4,2) -> 0.82644628 | R5: =MIN(R3/R4,2) -> 0.80991736 | S5: =T5 -> 1.5592287 | T5: =MIN(T3/(T4*3),2) -> 1.5592287 | U5: =MIN(U3/U4,2) -> 1.9338843 | V5: =MIN(V3/V4,2) -> 1.6147541 | W5: =X5 -> 1.9275362 | X5: =MIN(X3/(X4*3),2) -> 1.9275362 | Y5: =MIN(Y3/Y4,2) -> 2 | Z5: =MIN(Z3/Z4,2) -> 2 | AA5: =AB5 -> 2 | AB5: =MIN(AB3/(AB4*3),2) -> 2 | AC5: =MIN(AC3/AC4,2) -> 2 | AD5: =MIN(AD3/AD4,2) -> 2 | AE5: =AF5 -> 2 | AF5: =MIN(AF3/(AF4*3),2) -> 2
C6: YTD | E6: =AVERAGE($E$5:E5) -> 1.218543 | F6: =AVERAGE($E$5:F5) -> 1.2119205 | G6: =H5 -> 1.1103753 | I6: =(3*H5+I5)/4 -> 1.3327815 | J6: =(3*H5+I5+J5)/5 -> 1.4662252 | K6: =AVERAGE(H5,L5) -> 1.5518764 | M6: =(H5*3+L5*3+M5)/7 -> 1.615894 | N6: =(H5*3+L5*3+M5+N5)/8 -> 1.6326573 | O6: =AVERAGE(H5,L5,P5) -> 1.4771922 | Q6: =(H5*3+L5*3+P5*3+Q5)/10 -> 1.4121176 | R6: =(H5*3+L5*3+P5*3+Q5+R5)/11 -> 1.3573721 | S6: =AVERAGE(H5,L5,P5,T5) -> 1.4977013 | U6: =(SUM(3*T5,3*P5,3*L5,G5,F5))/12 -> 1.396156 | V6: =(SUM(3*T5,3*P5,3*L5,G5,U5))/12 -> 1.4568715 | W6: =AVERAGE(L5,P5,T5,X5) -> 1.7019915 | Y6: =(SUM(3*X5,3*T5,3*P5,K5,J5,Y5))/12 -> 1.6479076 | Z6: =(SUM(3*X5,3*T5,3*P5,K5,Y5,Z5))/12 -> 1.6479076 | AA6: =AVERAGE(P5,T5,X5,AB5) -> 1.7036471 | AC6: =(SUM(3*AB5,3*X5,3*T5,O5,N5,AC5))/12 -> 1.834329 | AD6: =(SUM(3*AB5,3*X5,3*T5,O5,AC5,AD5))/12 -> 1.8551623 | AE6: =AVERAGE(T5,X5,AB5,AF5) -> 1.8716912
C10: Q | D10: CARE Cards created by each employee with max of 6 during the quarter
C11: YTD Average Corrected | D11: Average CARE Cards for last 12 months based on Quarterly Calculations

Sheet Near Miss KPI Value
B1: Pillar | C1: KPI Name | D1: KPI Definition | E1: 2025 | N1: 2026
E2: 25-Apr | F2: 25-May | G2: 25-Jun | H2: 25-Jul | I2: 25-Aug | J2: 25-Sep | K2: 25-Oct | L2: 25-Nov | M2: 25-Dec | N2: 26-Jan | O2: 26-Feb | P2: 26-Mar | Q2: 26-Apr | R2: 26-May | S2: 46199 | T2: 46229 | U2: 46260 | V2: 46291 | W2: 46321 | X2: 46352 | Y2: 46382
B3: HSE | C3: # of Reported Near miss - Monthly | D3: KPI Guideline | E3: 114 | F3: 105 | G3: 80 | H3: 216 | I3: 247 | J3: 117 | K3: 283 | L3: 140 | M3: 122 | N3: 65 | O3: 46 | P3: 167 | Q3: 352 | R3: 49 | S3: 0
C4: # of Reported Near miss - YTD | E4: =SUM($E$3:E3) -> 114 | F4: =SUM($E$3:F3) -> 219 | G4: =SUM($E$3:G3) -> 299 | H4: =SUM($E$3:H3) -> 515 | I4: =SUM($E$3:I3) -> 762 | J4: =SUM($E$3:J3) -> 879 | K4: =SUM($E$3:K3) -> 1162 | L4: =SUM($E$3:L3) -> 1302 | ... P4: =SUM($E$3:P3) -> 1702 | Q4: =SUM(OFFSET(Q3,0,-11):Q3) -> 1940 | R4: =SUM(OFFSET(R3,0,-11):R3) -> 1884 | S4: =SUM(OFFSET(S3,0,-11):S3) -> 1804 | T4: =SUM(OFFSET(T3,0,-11):T3) -> 1588 | U4: =SUM(OFFSET(U3,0,-11):U3) -> 1341 | V4: =SUM(OFFSET(V3,0,-11):V3) -> 1224 | W4: =SUM(OFFSET(W3,0,-11):W3) -> 941 | X4: =SUM(OFFSET(X3,0,-11):X3) -> 801 | Y4: =SUM(OFFSET(Y3,0,-11):Y3) -> 679

Sheet Near Miss AutoCount
A2: Employee Status | B2: (Multiple Items)
A3: Near Miss | B3: Yes
A4: Status | B4: (Multiple Items)
A6: Count of Full Name / Nama Penuh
A7: 46

Sheet Value List
A1: 1 | B1: 2025
A2: 2 | B2: 2026
A3: 3
A4: 4
A5: 5
A6: 6
A7: 7
A8: 8
A9: 9
A10: 10
A11: 11
A12: 12
